<SceneText>
  <Speakers>
    <Section>Speaker</Section>
    <Entry>
      <PointerOffset>3656,3728</PointerOffset>
      <JapaneseText>&lt;Ines&gt;</JapaneseText>
      <EnglishText/>
      <Notes/>
      <Id>1</Id>
      <Status>To Do</Status>
    </Entry>
  </Speakers>
  <Strings>
    <Section>Struct</Section>
    <Entry>
      <PointerOffset>3276</PointerOffset>
      <JapaneseText>落下する途中
南の方角にオアシスが見えたわ</JapaneseText>
      <EnglishText/>
      <Notes/>
      <Id>1</Id>
      <StructId>1</StructId>
      <SpeakerId>1</SpeakerId>
      <UnknownPointer1>0</UnknownPointer1>
      <UnknownPointer2>3</UnknownPointer2>
      <Status>To Do</Status>
    </Entry>
    <Entry>
      <PointerOffset>3400</PointerOffset>
      <JapaneseText>一旦、シェヘラ砂漠の
オアシスに避難しましょう</JapaneseText>
      <EnglishText/>
      <Notes/>
      <Id>2</Id>
      <StructId>2</StructId>
      <SpeakerId>1</SpeakerId>
      <UnknownPointer1>0</UnknownPointer1>
      <UnknownPointer2>3</UnknownPointer2>
      <Status>To Do</Status>
    </Entry>
  </Strings>
  <Strings>
    <Section>Misc</Section>
    <Entry>
      <PointerOffset>2816</PointerOffset>
      <JapaneseText>%s</JapaneseText>
      <EnglishText/>
      <Notes/>
      <Id>3</Id>
      <Status>To Do</Status>
    </Entry>
  </Strings>
</SceneText>
