<SceneText>
  <Speakers>
    <Section>Speaker</Section>
    <Entry>
      <PointerOffset/>
      <JapaneseText>グロシュラー</JapaneseText>
      <EnglishText/>
      <Notes/>
      <Id>1</Id>
      <Status>To Do</Status>
    </Entry>
    <Entry>
      <PointerOffset/>
      <JapaneseText>アーカム</JapaneseText>
      <EnglishText/>
      <Notes/>
      <Id>2</Id>
      <Status>To Do</Status>
    </Entry>
    <Entry>
      <PointerOffset/>
      <JapaneseText>パライバ</JapaneseText>
      <EnglishText/>
      <Notes/>
      <Id>3</Id>
      <Status>To Do</Status>
    </Entry>
    <Entry>
      <PointerOffset/>
      <JapaneseText>カルセドニー</JapaneseText>
      <EnglishText/>
      <Notes/>
      <Id>4</Id>
      <Status>To Do</Status>
    </Entry>
    <Entry>
      <PointerOffset/>
      <JapaneseText>ペリドット</JapaneseText>
      <EnglishText/>
      <Notes/>
      <Id>5</Id>
      <Status>To Do</Status>
    </Entry>
    <Entry>
      <PointerOffset/>
      <JapaneseText>&lt;Ines&gt;</JapaneseText>
      <EnglishText/>
      <Notes/>
      <Id>6</Id>
      <Status>To Do</Status>
    </Entry>
    <Entry>
      <PointerOffset/>
      <JapaneseText>&lt;Hisui&gt;</JapaneseText>
      <EnglishText/>
      <Notes/>
      <Id>7</Id>
      <Status>To Do</Status>
    </Entry>
    <Entry>
      <PointerOffset/>
      <JapaneseText>&lt;Beryl&gt;</JapaneseText>
      <EnglishText/>
      <Notes/>
      <Id>8</Id>
      <Status>To Do</Status>
    </Entry>
    <Entry>
      <PointerOffset/>
      <JapaneseText>&lt;Shing&gt;</JapaneseText>
      <EnglishText/>
      <Notes/>
      <Id>9</Id>
      <Status>To Do</Status>
    </Entry>
    <Entry>
      <PointerOffset/>
      <JapaneseText>&lt;Kohaku&gt;</JapaneseText>
      <EnglishText/>
      <Notes/>
      <Id>10</Id>
      <Status>To Do</Status>
    </Entry>
    <Entry>
      <PointerOffset/>
      <JapaneseText>バイロクス</JapaneseText>
      <EnglishText/>
      <Notes/>
      <Id>11</Id>
      <Status>To Do</Status>
    </Entry>
    <Entry>
      <PointerOffset/>
      <JapaneseText>リチア</JapaneseText>
      <EnglishText/>
      <Notes/>
      <Id>12</Id>
      <Status>To Do</Status>
    </Entry>
    <Entry>
      <PointerOffset/>
      <JapaneseText>Variable</JapaneseText>
      <EnglishText/>
      <Notes/>
      <Id>13</Id>
      <Status>To Do</Status>
    </Entry>
  </Speakers>
  <Strings>
    <Section>Story</Section>
    <Entry>
      <PointerOffset>45872</PointerOffset>
      <VoiceId>S201801</VoiceId>
      <JapaneseText>くうう……なんという屈辱だ。
栄光あるマクス帝国城が
化物どもに汚されるとは！</JapaneseText>
      <EnglishText/>
      <Notes/>
      <SpeakerId>1</SpeakerId>
      <Id>1</Id>
      <BubbleId>1</BubbleId>
      <SubId>1</SubId>
      <Status>To Do</Status>
    </Entry>
    <Entry>
      <PointerOffset>46000</PointerOffset>
      <VoiceId>S201802</VoiceId>
      <JapaneseText>……安心しろ。もうすぐその
屈辱も消える。覚醒した黒い月
『ガルデニア』に吸い取られてな</JapaneseText>
      <EnglishText/>
      <Notes/>
      <SpeakerId>2</SpeakerId>
      <Id>2</Id>
      <BubbleId>1</BubbleId>
      <SubId>1</SubId>
      <Status>To Do</Status>
    </Entry>
    <Entry>
      <PointerOffset>46232</PointerOffset>
      <VoiceId>S201803</VoiceId>
      <JapaneseText>ラブラド！　貴様こうなる事を
知っておったのかッ？
なぜ今まで黙っておったッ!?</JapaneseText>
      <EnglishText/>
      <Notes/>
      <SpeakerId>1</SpeakerId>
      <Id>3</Id>
      <BubbleId>1</BubbleId>
      <SubId>1</SubId>
      <Status>To Do</Status>
    </Entry>
    <Entry>
      <PointerOffset>46440</PointerOffset>
      <VoiceId>S201804</VoiceId>
      <JapaneseText>くくく……ねむり姫のおとぎ話が
真実だと！　黒い月が化物だと！
話したら信じたか？　無理だッ</JapaneseText>
      <EnglishText/>
      <Notes/>
      <SpeakerId>2</SpeakerId>
      <Id>4</Id>
      <BubbleId>1</BubbleId>
      <SubId>1</SubId>
      <Status>To Do</Status>
    </Entry>
    <Entry>
      <PointerOffset>46440</PointerOffset>
      <VoiceId>S201805</VoiceId>
      <JapaneseText>結晶人の存在すら知らず
ただ争いを繰り返す、貴様ら
愚民に理解できるはずがない!!</JapaneseText>
      <EnglishText/>
      <Notes/>
      <SpeakerId>2</SpeakerId>
      <Id>4</Id>
      <BubbleId>2</BubbleId>
      <SubId>1</SubId>
      <Status>To Do</Status>
    </Entry>
    <Entry>
      <PointerOffset>46440</PointerOffset>
      <VoiceId>S201806</VoiceId>
      <JapaneseText>だから私は、マクス帝国の
力による世界統一に協力したのだ！</JapaneseText>
      <EnglishText/>
      <Notes/>
      <SpeakerId>2</SpeakerId>
      <Id>4</Id>
      <BubbleId>3</BubbleId>
      <SubId>1</SubId>
      <Status>To Do</Status>
    </Entry>
    <Entry>
      <PointerOffset>46440</PointerOffset>
      <VoiceId>S201807</VoiceId>
      <JapaneseText>結晶騎士団を組織し
今度こそソーマの力で
クリードを叩き潰すためにな！</JapaneseText>
      <EnglishText/>
      <Notes/>
      <SpeakerId>2</SpeakerId>
      <Id>4</Id>
      <BubbleId>4</BubbleId>
      <SubId>1</SubId>
      <Status>To Do</Status>
    </Entry>
    <Entry>
      <PointerOffset>46440</PointerOffset>
      <VoiceId>S201808</VoiceId>
      <JapaneseText>だがグロシュラー、貴様が
ソーマを破壊してくれたおかげで
全ては…………終わったわ……</JapaneseText>
      <EnglishText/>
      <Notes/>
      <SpeakerId>2</SpeakerId>
      <Id>4</Id>
      <BubbleId>5</BubbleId>
      <SubId>1</SubId>
      <Status>To Do</Status>
    </Entry>
    <Entry>
      <PointerOffset>46568</PointerOffset>
      <VoiceId>S201809</VoiceId>
      <JapaneseText>くっ……散々権力におぼれた
貴様が、いまさら救世主面で
ワシを責めるのか!?</JapaneseText>
      <EnglishText/>
      <Notes/>
      <SpeakerId>1</SpeakerId>
      <Id>5</Id>
      <BubbleId>1</BubbleId>
      <SubId>1</SubId>
      <Status>To Do</Status>
    </Entry>
    <Entry>
      <PointerOffset>46696</PointerOffset>
      <VoiceId>S201810</VoiceId>
      <JapaneseText>権力を求めて何が悪い!?
あのクリードに立ち向かうには
圧倒的な力が必要なのだ！</JapaneseText>
      <EnglishText/>
      <Notes/>
      <SpeakerId>2</SpeakerId>
      <Id>6</Id>
      <BubbleId>1</BubbleId>
      <SubId>1</SubId>
      <Status>To Do</Status>
    </Entry>
    <Entry>
      <PointerOffset>46696</PointerOffset>
      <VoiceId>S201811</VoiceId>
      <JapaneseText>……なのに、アイオラもドナも
ゼクスもテクタも……
皆、私を否定し去っていった……</JapaneseText>
      <EnglishText/>
      <Notes/>
      <SpeakerId>2</SpeakerId>
      <Id>6</Id>
      <BubbleId>2</BubbleId>
      <SubId>1</SubId>
      <Status>To Do</Status>
    </Entry>
    <Entry>
      <PointerOffset>46696</PointerOffset>
      <VoiceId>S201812</VoiceId>
      <JapaneseText>くくく……所詮、私の想いは
他人などにはわからぬ……例え
友や、実の息子であっても……な</JapaneseText>
      <EnglishText/>
      <Notes/>
      <SpeakerId>2</SpeakerId>
      <Id>6</Id>
      <BubbleId>3</BubbleId>
      <SubId>1</SubId>
      <Status>To Do</Status>
    </Entry>
    <Entry>
      <PointerOffset>46944</PointerOffset>
      <VoiceId>S201813</VoiceId>
      <JapaneseText>あの……カルセドニーは
どうなったのですか？</JapaneseText>
      <EnglishText/>
      <Notes/>
      <SpeakerId>3</SpeakerId>
      <Id>7</Id>
      <BubbleId>1</BubbleId>
      <SubId>1</SubId>
      <Status>To Do</Status>
    </Entry>
    <Entry>
      <PointerOffset>47268</PointerOffset>
      <VoiceId>S201814</VoiceId>
      <JapaneseText>あの者は処刑……
いや、尋問の最中に逃走しました</JapaneseText>
      <EnglishText/>
      <Notes/>
      <SpeakerId>1</SpeakerId>
      <Id>8</Id>
      <BubbleId>1</BubbleId>
      <SubId>1</SubId>
      <Status>To Do</Status>
    </Entry>
    <Entry>
      <PointerOffset>47268</PointerOffset>
      <VoiceId>S201815</VoiceId>
      <JapaneseText>そう、パライバ様との
約束を破ったとか
言い残しておりましたな？</JapaneseText>
      <EnglishText/>
      <Notes/>
      <SpeakerId>1</SpeakerId>
      <Id>8</Id>
      <BubbleId>2</BubbleId>
      <SubId>1</SubId>
      <Status>To Do</Status>
    </Entry>
    <Entry>
      <PointerOffset>47396</PointerOffset>
      <VoiceId>S201816</VoiceId>
      <JapaneseText>そんな……うそです！</JapaneseText>
      <EnglishText/>
      <Notes/>
      <SpeakerId>3</SpeakerId>
      <Id>9</Id>
      <BubbleId>1</BubbleId>
      <SubId>1</SubId>
      <Status>To Do</Status>
    </Entry>
    <Entry>
      <PointerOffset>47524</PointerOffset>
      <VoiceId>S201817</VoiceId>
      <JapaneseText>う、うそではありませぬ！</JapaneseText>
      <EnglishText/>
      <Notes/>
      <SpeakerId>1</SpeakerId>
      <Id>10</Id>
      <BubbleId>1</BubbleId>
      <SubId>1</SubId>
      <Status>To Do</Status>
    </Entry>
    <Entry>
      <PointerOffset>47524</PointerOffset>
      <VoiceId>S201818</VoiceId>
      <JapaneseText>その証拠に、あのガキは
約束のペンダントとやらを
放り出して逃げおったのです！</JapaneseText>
      <EnglishText/>
      <Notes/>
      <SpeakerId>1</SpeakerId>
      <Id>10</Id>
      <BubbleId>2</BubbleId>
      <SubId>1</SubId>
      <Status>To Do</Status>
    </Entry>
    <Entry>
      <PointerOffset>48868</PointerOffset>
      <VoiceId>S201819</VoiceId>
      <JapaneseText>本物の緋眼石のペンダント……
そんな……わたくしを守ると
約束してくれたのに……</JapaneseText>
      <EnglishText/>
      <Notes/>
      <SpeakerId>3</SpeakerId>
      <Id>11</Id>
      <BubbleId>1</BubbleId>
      <SubId>1</SubId>
      <Status>To Do</Status>
    </Entry>
    <Entry>
      <PointerOffset>50048</PointerOffset>
      <VoiceId>S201820</VoiceId>
      <JapaneseText>おお、我が軍の救援か!?</JapaneseText>
      <EnglishText/>
      <Notes/>
      <SpeakerId>1</SpeakerId>
      <Id>12</Id>
      <BubbleId>1</BubbleId>
      <SubId>1</SubId>
      <Status>To Do</Status>
    </Entry>
    <Entry>
      <PointerOffset>53096</PointerOffset>
      <VoiceId>S201821</VoiceId>
      <JapaneseText>カルにも見捨てられてしまった……
…………いいえ、最初から
わかってゐタ事…………</JapaneseText>
      <EnglishText/>
      <Notes/>
      <SpeakerId>3</SpeakerId>
      <Id>13</Id>
      <BubbleId>1</BubbleId>
      <SubId>1</SubId>
      <Status>To Do</Status>
    </Entry>
    <Entry>
      <PointerOffset>53096</PointerOffset>
      <VoiceId>S201822</VoiceId>
      <JapaneseText>誰もワタクシを
人とシて見てイなゐと……
愛シてなどくれナイと……</JapaneseText>
      <EnglishText/>
      <Notes/>
      <SpeakerId>3</SpeakerId>
      <Id>13</Id>
      <BubbleId>2</BubbleId>
      <SubId>1</SubId>
      <Status>To Do</Status>
    </Entry>
    <Entry>
      <PointerOffset>53096</PointerOffset>
      <VoiceId>S201823</VoiceId>
      <JapaneseText>そう、おサなき頃から
ずッと、アきラめてゐた事ォ……ッ</JapaneseText>
      <EnglishText/>
      <Notes/>
      <SpeakerId>3</SpeakerId>
      <Id>13</Id>
      <BubbleId>3</BubbleId>
      <SubId>1</SubId>
      <Status>To Do</Status>
    </Entry>
    <Entry>
      <PointerOffset>53304</PointerOffset>
      <VoiceId>S201824</VoiceId>
      <JapaneseText>…………陛下？</JapaneseText>
      <EnglishText/>
      <Notes/>
      <SpeakerId>2</SpeakerId>
      <Id>14</Id>
      <BubbleId>1</BubbleId>
      <SubId>1</SubId>
      <Status>To Do</Status>
    </Entry>
    <Entry>
      <PointerOffset>54956</PointerOffset>
      <VoiceId>S201825</VoiceId>
      <JapaneseText>ならば、ワタクシもいラないィ！
もうダレも！　なにモッ!!
わダくしジシンさえもぉぉぉッ!!</JapaneseText>
      <EnglishText/>
      <Notes/>
      <SpeakerId>3</SpeakerId>
      <Id>15</Id>
      <BubbleId>1</BubbleId>
      <SubId>1</SubId>
      <Status>To Do</Status>
    </Entry>
    <Entry>
      <PointerOffset>60616</PointerOffset>
      <VoiceId>S201826</VoiceId>
      <JapaneseText>き、貴様ら!!
この化物をなんとかしろ……
むぐぁ……ッッ</JapaneseText>
      <EnglishText/>
      <Notes/>
      <SpeakerId>1</SpeakerId>
      <Id>16</Id>
      <BubbleId>1</BubbleId>
      <SubId>1</SubId>
      <Status>To Do</Status>
    </Entry>
    <Entry>
      <PointerOffset>60744</PointerOffset>
      <VoiceId>S201827</VoiceId>
      <JapaneseText>ひぃぃ！
く、来るなぁぁッ！
なぜこんな事にぃ……うごぉぉッ!!</JapaneseText>
      <EnglishText/>
      <Notes/>
      <SpeakerId>2</SpeakerId>
      <Id>17</Id>
      <BubbleId>1</BubbleId>
      <SubId>1</SubId>
      <Status>To Do</Status>
    </Entry>
    <Entry>
      <PointerOffset>60872</PointerOffset>
      <VoiceId>S201828</VoiceId>
      <JapaneseText>父上ッ……上将ッ!!</JapaneseText>
      <EnglishText/>
      <Notes/>
      <SpeakerId>4</SpeakerId>
      <Id>18</Id>
      <BubbleId>1</BubbleId>
      <SubId>1</SubId>
      <Status>To Do</Status>
    </Entry>
    <Entry>
      <PointerOffset>61000</PointerOffset>
      <VoiceId>S201829</VoiceId>
      <JapaneseText>うわッ！
何がやばいのかわかんないほど
やっっばい状況!!</JapaneseText>
      <EnglishText/>
      <Notes/>
      <SpeakerId>5</SpeakerId>
      <Id>19</Id>
      <BubbleId>1</BubbleId>
      <SubId>1</SubId>
      <Status>To Do</Status>
    </Entry>
    <Entry>
      <PointerOffset>61128</PointerOffset>
      <VoiceId>S201830</VoiceId>
      <JapaneseText>これは……複数の人間を
とりこんだゼロム融合ッ!?
しかも本体は……</JapaneseText>
      <EnglishText/>
      <Notes/>
      <SpeakerId>6</SpeakerId>
      <Id>20</Id>
      <BubbleId>1</BubbleId>
      <SubId>1</SubId>
      <Status>To Do</Status>
    </Entry>
    <Entry>
      <PointerOffset>61256</PointerOffset>
      <VoiceId>S201831</VoiceId>
      <JapaneseText>なにィィぃモぉぉぉッ
イらナぁイぃぃ〜〜〜ッ！！！</JapaneseText>
      <EnglishText/>
      <Notes/>
      <SpeakerId>3</SpeakerId>
      <Id>21</Id>
      <BubbleId>1</BubbleId>
      <SubId>1</SubId>
      <Status>To Do</Status>
    </Entry>
    <Entry>
      <PointerOffset>61504</PointerOffset>
      <VoiceId>S201832</VoiceId>
      <JapaneseText>パライバ様ッ！！？</JapaneseText>
      <EnglishText/>
      <Notes/>
      <SpeakerId>4</SpeakerId>
      <Id>22</Id>
      <BubbleId>1</BubbleId>
      <SubId>1</SubId>
      <Status>To Do</Status>
    </Entry>
    <Entry>
      <PointerOffset>62608</PointerOffset>
      <VoiceId>S201833</VoiceId>
      <JapaneseText>ヴるるぅぅぅ〜〜〜〜
〜〜〜〜〜〜〜〜〜〜〜
〜〜〜〜〜〜〜〜〜ッッ！！！</JapaneseText>
      <EnglishText/>
      <Notes/>
      <SpeakerId>3</SpeakerId>
      <Id>23</Id>
      <BubbleId>1</BubbleId>
      <SubId>1</SubId>
      <Status>To Do</Status>
    </Entry>
    <Entry>
      <PointerOffset>63652</PointerOffset>
      <VoiceId>S201834</VoiceId>
      <JapaneseText>バカ野郎！　この非常時に
お偉いさんがまとめてゼロムに
取りこまれてどうすんだよッ</JapaneseText>
      <EnglishText/>
      <Notes/>
      <SpeakerId>7</SpeakerId>
      <Id>24</Id>
      <BubbleId>1</BubbleId>
      <SubId>1</SubId>
      <Status>To Do</Status>
    </Entry>
    <Entry>
      <PointerOffset>63780</PointerOffset>
      <VoiceId>S201835</VoiceId>
      <JapaneseText>て、提案だけど、放っといて
『白化』させちゃうってのはどう？</JapaneseText>
      <EnglishText/>
      <Notes/>
      <SpeakerId>8</SpeakerId>
      <Id>25</Id>
      <BubbleId>1</BubbleId>
      <SubId>1</SubId>
      <Status>To Do</Status>
    </Entry>
    <Entry>
      <PointerOffset>64452</PointerOffset>
      <VoiceId>S201836</VoiceId>
      <JapaneseText>……な〜んていう奴は
許せないよねっ！</JapaneseText>
      <EnglishText/>
      <Notes/>
      <SpeakerId>8</SpeakerId>
      <Id>26</Id>
      <BubbleId>1</BubbleId>
      <SubId>1</SubId>
      <Status>To Do</Status>
    </Entry>
    <Entry>
      <PointerOffset>65612</PointerOffset>
      <VoiceId>S201837</VoiceId>
      <JapaneseText>パライバ様ッ！
今、お助けします!!</JapaneseText>
      <EnglishText/>
      <Notes/>
      <SpeakerId>4</SpeakerId>
      <Id>27</Id>
      <BubbleId>1</BubbleId>
      <SubId>1</SubId>
      <Status>To Do</Status>
    </Entry>
    <Entry>
      <PointerOffset>66816</PointerOffset>
      <VoiceId>S201838</VoiceId>
      <JapaneseText>ぐはぁッ!!</JapaneseText>
      <EnglishText/>
      <Notes/>
      <SpeakerId>4</SpeakerId>
      <Id>28</Id>
      <BubbleId>1</BubbleId>
      <SubId>1</SubId>
      <Status>To Do</Status>
    </Entry>
    <Entry>
      <PointerOffset>67480</PointerOffset>
      <VoiceId>S201839</VoiceId>
      <JapaneseText>無理するなよ！
お前、さっきゼロムに
やられた傷が治ってないだろ？</JapaneseText>
      <EnglishText/>
      <Notes/>
      <SpeakerId>9</SpeakerId>
      <Id>29</Id>
      <BubbleId>1</BubbleId>
      <SubId>1</SubId>
      <Status>To Do</Status>
    </Entry>
    <Entry>
      <PointerOffset>67744</PointerOffset>
      <VoiceId>S201840</VoiceId>
      <JapaneseText>うるさい！
例え手足が千切れようとも
パライバ様は僕が助けるんだッ!!</JapaneseText>
      <EnglishText/>
      <Notes/>
      <SpeakerId>4</SpeakerId>
      <Id>30</Id>
      <BubbleId>1</BubbleId>
      <SubId>1</SubId>
      <Status>To Do</Status>
    </Entry>
    <Entry>
      <PointerOffset>68660</PointerOffset>
      <VoiceId>S201841</VoiceId>
      <JapaneseText>ああ。オレたちはゼロムの動きを
とめる。その後にマリンさんの
スピリアを助けるのはお前だ！</JapaneseText>
      <EnglishText/>
      <Notes/>
      <SpeakerId>9</SpeakerId>
      <Id>31</Id>
      <BubbleId>1</BubbleId>
      <SubId>1</SubId>
      <Status>To Do</Status>
    </Entry>
    <Entry>
      <PointerOffset>70980</PointerOffset>
      <VoiceId>S201901</VoiceId>
      <JapaneseText>イらナイぃぃぃ……ッ
なにィィ……もォォ〜〜ッ</JapaneseText>
      <EnglishText/>
      <Notes/>
      <SpeakerId>3</SpeakerId>
      <Id>32</Id>
      <BubbleId>1</BubbleId>
      <SubId>1</SubId>
      <Status>To Do</Status>
    </Entry>
    <Entry>
      <PointerOffset>71108</PointerOffset>
      <VoiceId>S201902</VoiceId>
      <JapaneseText>くそッ、まだ動くのか!?
でも、これ以上攻撃すると
マリンさんを殺しちゃう……</JapaneseText>
      <EnglishText/>
      <Notes/>
      <SpeakerId>9</SpeakerId>
      <Id>33</Id>
      <BubbleId>1</BubbleId>
      <SubId>1</SubId>
      <Status>To Do</Status>
    </Entry>
    <Entry>
      <PointerOffset>71236</PointerOffset>
      <VoiceId>S201903</VoiceId>
      <JapaneseText>近寄ルなァァぁ〜〜〜ッッ!!</JapaneseText>
      <EnglishText/>
      <Notes/>
      <SpeakerId>3</SpeakerId>
      <Id>34</Id>
      <BubbleId>1</BubbleId>
      <SubId>1</SubId>
      <Status>To Do</Status>
    </Entry>
    <Entry>
      <PointerOffset>71840</PointerOffset>
      <VoiceId>S201904</VoiceId>
      <JapaneseText>きゃぁぁッ！</JapaneseText>
      <EnglishText/>
      <Notes/>
      <SpeakerId>10</SpeakerId>
      <Id>35</Id>
      <BubbleId>1</BubbleId>
      <SubId>1</SubId>
      <Status>To Do</Status>
    </Entry>
    <Entry>
      <PointerOffset>73832</PointerOffset>
      <VoiceId>S201905</VoiceId>
      <JapaneseText>ぐッ……
&lt;Shing&gt;、&lt;Kohaku&gt;……
ここからは僕に任せてくれ</JapaneseText>
      <EnglishText/>
      <Notes/>
      <SpeakerId>4</SpeakerId>
      <Id>36</Id>
      <BubbleId>1</BubbleId>
      <SubId>1</SubId>
      <Status>To Do</Status>
    </Entry>
    <Entry>
      <PointerOffset>74120</PointerOffset>
      <VoiceId>S201906</VoiceId>
      <JapaneseText>あたしからも頼むよ！
ここだけは、隊長が意地を
見せなきゃいけないトコなんだ</JapaneseText>
      <EnglishText/>
      <Notes/>
      <SpeakerId>5</SpeakerId>
      <Id>37</Id>
      <BubbleId>1</BubbleId>
      <SubId>1</SubId>
      <Status>To Do</Status>
    </Entry>
    <Entry>
      <PointerOffset>74780</PointerOffset>
      <VoiceId>S201907</VoiceId>
      <JapaneseText>……わかった。
頼んだぜ、カルッ！</JapaneseText>
      <EnglishText/>
      <Notes/>
      <SpeakerId>9</SpeakerId>
      <Id>38</Id>
      <BubbleId>1</BubbleId>
      <SubId>1</SubId>
      <Status>To Do</Status>
    </Entry>
    <Entry>
      <PointerOffset>76752</PointerOffset>
      <VoiceId>S201908</VoiceId>
      <JapaneseText>パライバ様……
僕は、ただあなたの
笑顔が見たかったのです</JapaneseText>
      <EnglishText/>
      <Notes/>
      <SpeakerId>4</SpeakerId>
      <Id>39</Id>
      <BubbleId>1</BubbleId>
      <SubId>1</SubId>
      <Status>To Do</Status>
    </Entry>
    <Entry>
      <PointerOffset>76752</PointerOffset>
      <VoiceId>S201909</VoiceId>
      <JapaneseText>でも、どうしたらあなたが
笑ってくれるのかわからなかった</JapaneseText>
      <EnglishText/>
      <Notes/>
      <SpeakerId>4</SpeakerId>
      <Id>39</Id>
      <BubbleId>2</BubbleId>
      <SubId>1</SubId>
      <Status>To Do</Status>
    </Entry>
    <Entry>
      <PointerOffset>76752</PointerOffset>
      <VoiceId>S201910</VoiceId>
      <JapaneseText>だから
あなたを苦しめている世界を
僕の力で変えようと思った……</JapaneseText>
      <EnglishText/>
      <Notes/>
      <SpeakerId>4</SpeakerId>
      <Id>39</Id>
      <BubbleId>3</BubbleId>
      <SubId>1</SubId>
      <Status>To Do</Status>
    </Entry>
    <Entry>
      <PointerOffset>76880</PointerOffset>
      <VoiceId>S201911</VoiceId>
      <JapaneseText>ヴるるぅッ！！！</JapaneseText>
      <EnglishText/>
      <Notes/>
      <SpeakerId>3</SpeakerId>
      <Id>40</Id>
      <BubbleId>1</BubbleId>
      <SubId>1</SubId>
      <Status>To Do</Status>
    </Entry>
    <Entry>
      <PointerOffset>78296</PointerOffset>
      <VoiceId>S201912</VoiceId>
      <JapaneseText>……以前、このバカから
言われました</JapaneseText>
      <EnglishText/>
      <Notes/>
      <SpeakerId>4</SpeakerId>
      <Id>41</Id>
      <BubbleId>1</BubbleId>
      <SubId>1</SubId>
      <Status>To Do</Status>
    </Entry>
    <Entry>
      <PointerOffset>78296</PointerOffset>
      <VoiceId>S201913</VoiceId>
      <JapaneseText>『目の前の女の子の
笑顔も取り戻せない奴に
世界を救えるはずがない』と</JapaneseText>
      <EnglishText/>
      <Notes/>
      <SpeakerId>4</SpeakerId>
      <Id>41</Id>
      <BubbleId>2</BubbleId>
      <SubId>1</SubId>
      <Status>To Do</Status>
    </Entry>
    <Entry>
      <PointerOffset>78424</PointerOffset>
      <VoiceId>S201914</VoiceId>
      <JapaneseText>…………ヴるぅッ！！！</JapaneseText>
      <EnglishText/>
      <Notes/>
      <SpeakerId>3</SpeakerId>
      <Id>42</Id>
      <BubbleId>1</BubbleId>
      <SubId>1</SubId>
      <Status>To Do</Status>
    </Entry>
    <Entry>
      <PointerOffset>80884</PointerOffset>
      <VoiceId>S201915</VoiceId>
      <JapaneseText>悔しいけど、このバカの言う通り
だった。僕が何より先に
しなければいけなかったのは——</JapaneseText>
      <EnglishText/>
      <Notes/>
      <SpeakerId>4</SpeakerId>
      <Id>43</Id>
      <BubbleId>1</BubbleId>
      <SubId>1</SubId>
      <Status>To Do</Status>
    </Entry>
    <Entry>
      <PointerOffset>80884</PointerOffset>
      <VoiceId>S201916</VoiceId>
      <JapaneseText>この胸の想いを
あなたに伝える事だったのです！</JapaneseText>
      <EnglishText/>
      <Notes/>
      <SpeakerId>4</SpeakerId>
      <Id>43</Id>
      <BubbleId>2</BubbleId>
      <SubId>1</SubId>
      <Status>To Do</Status>
    </Entry>
    <Entry>
      <PointerOffset>81796</PointerOffset>
      <VoiceId>S201917</VoiceId>
      <JapaneseText>カるぅ……逃ゲて……！
アなたを……殺しテしまヴ……ッ!!</JapaneseText>
      <EnglishText/>
      <Notes/>
      <SpeakerId>3</SpeakerId>
      <Id>44</Id>
      <BubbleId>1</BubbleId>
      <SubId>1</SubId>
      <Status>To Do</Status>
    </Entry>
    <Entry>
      <PointerOffset>82364</PointerOffset>
      <VoiceId>S201918</VoiceId>
      <JapaneseText>パライバ＝マリン＝ド＝レ様。
初めてお会いした時から
僕は……</JapaneseText>
      <EnglishText/>
      <Notes/>
      <SpeakerId>4</SpeakerId>
      <Id>45</Id>
      <BubbleId>1</BubbleId>
      <SubId>1</SubId>
      <Status>To Do</Status>
    </Entry>
    <Entry>
      <PointerOffset>82364</PointerOffset>
      <VoiceId>S201919</VoiceId>
      <JapaneseText>あなたを愛していましたッ！</JapaneseText>
      <EnglishText/>
      <Notes/>
      <SpeakerId>4</SpeakerId>
      <Id>45</Id>
      <BubbleId>2</BubbleId>
      <SubId>1</SubId>
      <Status>To Do</Status>
    </Entry>
    <Entry>
      <PointerOffset>83496</PointerOffset>
      <VoiceId>S201920</VoiceId>
      <JapaneseText>そしてこれからも……
ここであなたに殺されようとも！
永遠にですッ!!</JapaneseText>
      <EnglishText/>
      <Notes/>
      <SpeakerId>4</SpeakerId>
      <Id>46</Id>
      <BubbleId>1</BubbleId>
      <SubId>1</SubId>
      <Status>To Do</Status>
    </Entry>
    <Entry>
      <PointerOffset>84560</PointerOffset>
      <VoiceId>S201921</VoiceId>
      <JapaneseText>アぁぁ…………イや……ッ
殺したく……ナイぃぃッ！
ワたクシも……かるヲォォ……</JapaneseText>
      <EnglishText/>
      <Notes/>
      <SpeakerId>3</SpeakerId>
      <Id>47</Id>
      <BubbleId>1</BubbleId>
      <SubId>1</SubId>
      <Status>To Do</Status>
    </Entry>
    <Entry>
      <PointerOffset>84964</PointerOffset>
      <VoiceId>S201922</VoiceId>
      <JapaneseText>……愛シてイルからァァッッ！！！</JapaneseText>
      <EnglishText/>
      <Notes/>
      <SpeakerId>3</SpeakerId>
      <Id>48</Id>
      <BubbleId>1</BubbleId>
      <SubId>1</SubId>
      <Status>To Do</Status>
    </Entry>
    <Entry>
      <PointerOffset>85996</PointerOffset>
      <VoiceId>S201923</VoiceId>
      <JapaneseText>パライバ様ッッ！！！</JapaneseText>
      <EnglishText/>
      <Notes/>
      <SpeakerId>4</SpeakerId>
      <Id>49</Id>
      <BubbleId>1</BubbleId>
      <SubId>1</SubId>
      <Status>To Do</Status>
    </Entry>
    <Entry>
      <PointerOffset>88344</PointerOffset>
      <VoiceId>S201924</VoiceId>
      <JapaneseText>パライバ様ッ！
パライバ様ッッ!!</JapaneseText>
      <EnglishText/>
      <Notes/>
      <SpeakerId>4</SpeakerId>
      <Id>50</Id>
      <BubbleId>1</BubbleId>
      <SubId>1</SubId>
      <Status>To Do</Status>
    </Entry>
    <Entry>
      <PointerOffset>88472</PointerOffset>
      <VoiceId>S201925</VoiceId>
      <JapaneseText>よかっ……た……
カルセドニー……
……生きています……ね？</JapaneseText>
      <EnglishText/>
      <Notes/>
      <SpeakerId>3</SpeakerId>
      <Id>51</Id>
      <BubbleId>1</BubbleId>
      <SubId>1</SubId>
      <Status>To Do</Status>
    </Entry>
    <Entry>
      <PointerOffset>88600</PointerOffset>
      <VoiceId>S201926</VoiceId>
      <JapaneseText>それはこちらのセリフです！
お体はなんともないのですかッ!?</JapaneseText>
      <EnglishText/>
      <Notes/>
      <SpeakerId>4</SpeakerId>
      <Id>52</Id>
      <BubbleId>1</BubbleId>
      <SubId>1</SubId>
      <Status>To Do</Status>
    </Entry>
    <Entry>
      <PointerOffset>88728</PointerOffset>
      <VoiceId>S201927</VoiceId>
      <JapaneseText>うう……
足の感覚が……ない……!?</JapaneseText>
      <EnglishText/>
      <Notes/>
      <SpeakerId>3</SpeakerId>
      <Id>53</Id>
      <BubbleId>1</BubbleId>
      <SubId>1</SubId>
      <Status>To Do</Status>
    </Entry>
    <Entry>
      <PointerOffset>88856</PointerOffset>
      <VoiceId>S201928</VoiceId>
      <JapaneseText>足が……？
そうか、僕をかばったせいで……</JapaneseText>
      <EnglishText/>
      <Notes/>
      <SpeakerId>4</SpeakerId>
      <Id>54</Id>
      <BubbleId>1</BubbleId>
      <SubId>1</SubId>
      <Status>To Do</Status>
    </Entry>
    <Entry>
      <PointerOffset>88984</PointerOffset>
      <VoiceId>S201929</VoiceId>
      <JapaneseText>あなたの命を守れたなら
もう二度と動かなくても
後悔はありません。それより……</JapaneseText>
      <EnglishText/>
      <Notes/>
      <SpeakerId>3</SpeakerId>
      <Id>55</Id>
      <BubbleId>1</BubbleId>
      <SubId>1</SubId>
      <Status>To Do</Status>
    </Entry>
    <Entry>
      <PointerOffset>88984</PointerOffset>
      <VoiceId>S201930</VoiceId>
      <JapaneseText>…………くすっ</JapaneseText>
      <EnglishText/>
      <Notes/>
      <SpeakerId>3</SpeakerId>
      <Id>55</Id>
      <BubbleId>2</BubbleId>
      <SubId>1</SubId>
      <Status>To Do</Status>
    </Entry>
    <Entry>
      <PointerOffset>89112</PointerOffset>
      <VoiceId>S201931</VoiceId>
      <JapaneseText>パライバ……様？</JapaneseText>
      <EnglishText/>
      <Notes/>
      <SpeakerId>4</SpeakerId>
      <Id>56</Id>
      <BubbleId>1</BubbleId>
      <SubId>1</SubId>
      <Status>To Do</Status>
    </Entry>
    <Entry>
      <PointerOffset>89240</PointerOffset>
      <VoiceId>S201932</VoiceId>
      <JapaneseText>……ごめんなさい。
あなたが覚えていないのは、
当然なのですけど</JapaneseText>
      <EnglishText/>
      <Notes/>
      <SpeakerId>3</SpeakerId>
      <Id>57</Id>
      <BubbleId>1</BubbleId>
      <SubId>1</SubId>
      <Status>To Do</Status>
    </Entry>
    <Entry>
      <PointerOffset>89240</PointerOffset>
      <VoiceId>S201933</VoiceId>
      <JapaneseText>わたくしたちが
『初めて会った』のは
あなたが赤ちゃんの時なのですよ？</JapaneseText>
      <EnglishText/>
      <Notes/>
      <SpeakerId>3</SpeakerId>
      <Id>57</Id>
      <BubbleId>2</BubbleId>
      <SubId>1</SubId>
      <Status>To Do</Status>
    </Entry>
    <Entry>
      <PointerOffset>89368</PointerOffset>
      <VoiceId>S201934</VoiceId>
      <JapaneseText>ええ!?
僕が少年騎士の称号を
いただきに登城した時でしょう？</JapaneseText>
      <EnglishText/>
      <Notes/>
      <SpeakerId>4</SpeakerId>
      <Id>58</Id>
      <BubbleId>1</BubbleId>
      <SubId>1</SubId>
      <Status>To Do</Status>
    </Entry>
    <Entry>
      <PointerOffset>92664</PointerOffset>
      <VoiceId>S201935</VoiceId>
      <JapaneseText>いいえ。わたくし
あなたのオムツを代えて
あげた事もありますもの</JapaneseText>
      <EnglishText/>
      <Notes/>
      <SpeakerId>3</SpeakerId>
      <Id>59</Id>
      <BubbleId>1</BubbleId>
      <SubId>1</SubId>
      <Status>To Do</Status>
    </Entry>
    <Entry>
      <PointerOffset>92664</PointerOffset>
      <VoiceId>S201936</VoiceId>
      <JapaneseText>あの時、あなたが、わたくしを
好きになってくれたのかしらと
思ったら……おかしくて</JapaneseText>
      <EnglishText/>
      <Notes/>
      <SpeakerId>3</SpeakerId>
      <Id>59</Id>
      <BubbleId>2</BubbleId>
      <SubId>1</SubId>
      <Status>To Do</Status>
    </Entry>
    <Entry>
      <PointerOffset>92792</PointerOffset>
      <VoiceId>S201937</VoiceId>
      <JapaneseText>オ、オムツを代えた!?
そんなぁ…………</JapaneseText>
      <EnglishText/>
      <Notes/>
      <SpeakerId>4</SpeakerId>
      <Id>60</Id>
      <BubbleId>1</BubbleId>
      <SubId>1</SubId>
      <Status>To Do</Status>
    </Entry>
    <Entry>
      <PointerOffset>93108</PointerOffset>
      <VoiceId>S201938</VoiceId>
      <JapaneseText>…………見られたな</JapaneseText>
      <EnglishText/>
      <Notes/>
      <SpeakerId>9</SpeakerId>
      <Id>61</Id>
      <BubbleId>1</BubbleId>
      <SubId>1</SubId>
      <Status>To Do</Status>
    </Entry>
    <Entry>
      <PointerOffset>94400</PointerOffset>
      <VoiceId>S201939</VoiceId>
      <JapaneseText>……あの赤ちゃんが
こんなにも頼もしい騎士に
育ったのですね</JapaneseText>
      <EnglishText/>
      <Notes/>
      <SpeakerId>3</SpeakerId>
      <Id>62</Id>
      <BubbleId>1</BubbleId>
      <SubId>1</SubId>
      <Status>To Do</Status>
    </Entry>
    <Entry>
      <PointerOffset>94400</PointerOffset>
      <VoiceId>S201940</VoiceId>
      <JapaneseText>それに比べて、わたくしはなんと
情けない皇帝なのでしょう……</JapaneseText>
      <EnglishText/>
      <Notes/>
      <SpeakerId>3</SpeakerId>
      <Id>62</Id>
      <BubbleId>2</BubbleId>
      <SubId>1</SubId>
      <Status>To Do</Status>
    </Entry>
    <Entry>
      <PointerOffset>94872</PointerOffset>
      <VoiceId>S201941</VoiceId>
      <JapaneseText>おそれながら。過ちに気付いたら
正せば良いのです。今こそ世界は
陛下の御力を必要としています</JapaneseText>
      <EnglishText/>
      <Notes/>
      <SpeakerId>6</SpeakerId>
      <Id>63</Id>
      <BubbleId>1</BubbleId>
      <SubId>1</SubId>
      <Status>To Do</Status>
    </Entry>
    <Entry>
      <PointerOffset>95000</PointerOffset>
      <VoiceId>S201942</VoiceId>
      <JapaneseText>んぐぁ……
一体何がどうなって……？</JapaneseText>
      <EnglishText/>
      <Notes/>
      <SpeakerId>1</SpeakerId>
      <Id>64</Id>
      <BubbleId>1</BubbleId>
      <SubId>1</SubId>
      <Status>To Do</Status>
    </Entry>
    <Entry>
      <PointerOffset>95128</PointerOffset>
      <VoiceId>S201943</VoiceId>
      <JapaneseText>くぅぅ……頭が割れそうだ……</JapaneseText>
      <EnglishText/>
      <Notes/>
      <SpeakerId>2</SpeakerId>
      <Id>65</Id>
      <BubbleId>1</BubbleId>
      <SubId>1</SubId>
      <Status>To Do</Status>
    </Entry>
    <Entry>
      <PointerOffset>95412</PointerOffset>
      <VoiceId>S201944</VoiceId>
      <JapaneseText>せめて今できる事をやらねば
あなたたちと共に笑う
資格はありませんわね</JapaneseText>
      <EnglishText/>
      <Notes/>
      <SpeakerId>3</SpeakerId>
      <Id>66</Id>
      <BubbleId>1</BubbleId>
      <SubId>1</SubId>
      <Status>To Do</Status>
    </Entry>
    <Entry>
      <PointerOffset>95700</PointerOffset>
      <VoiceId>S201945</VoiceId>
      <JapaneseText>グロシュラー上将！
大至急、突撃部隊を編成。
城に入りこんだ化物を一掃なさい！</JapaneseText>
      <EnglishText/>
      <Notes/>
      <SpeakerId>3</SpeakerId>
      <Id>67</Id>
      <BubbleId>1</BubbleId>
      <SubId>1</SubId>
      <Status>To Do</Status>
    </Entry>
    <Entry>
      <PointerOffset>95700</PointerOffset>
      <VoiceId>S201946</VoiceId>
      <JapaneseText>城内戦闘の際、器物の被害は
一切考慮しなくてかまいません</JapaneseText>
      <EnglishText/>
      <Notes/>
      <SpeakerId>3</SpeakerId>
      <Id>67</Id>
      <BubbleId>2</BubbleId>
      <SubId>1</SubId>
      <Status>To Do</Status>
    </Entry>
    <Entry>
      <PointerOffset>95828</PointerOffset>
      <VoiceId>S201947</VoiceId>
      <JapaneseText>は…………!?</JapaneseText>
      <EnglishText/>
      <Notes/>
      <SpeakerId>1</SpeakerId>
      <Id>68</Id>
      <BubbleId>1</BubbleId>
      <SubId>1</SubId>
      <Status>To Do</Status>
    </Entry>
    <Entry>
      <PointerOffset>95956</PointerOffset>
      <VoiceId>S201948</VoiceId>
      <JapaneseText>聞こえませんでしたか？
耳が遠くなったのなら
代わりの者に申し付けましょう</JapaneseText>
      <EnglishText/>
      <Notes/>
      <SpeakerId>3</SpeakerId>
      <Id>69</Id>
      <BubbleId>1</BubbleId>
      <SubId>1</SubId>
      <Status>To Do</Status>
    </Entry>
    <Entry>
      <PointerOffset>96204</PointerOffset>
      <VoiceId>S201949</VoiceId>
      <JapaneseText>い、いえッ！
マクス帝国皇帝パライバ陛下！
勅命、かしこまってござるッ!!</JapaneseText>
      <EnglishText/>
      <Notes/>
      <SpeakerId>1</SpeakerId>
      <Id>70</Id>
      <BubbleId>1</BubbleId>
      <SubId>1</SubId>
      <Status>To Do</Status>
    </Entry>
    <Entry>
      <PointerOffset>96332</PointerOffset>
      <VoiceId>S201950</VoiceId>
      <JapaneseText>アーカム教主！
結晶騎士団は帝都民の
救護と避難を担当してください！</JapaneseText>
      <EnglishText/>
      <Notes/>
      <SpeakerId>3</SpeakerId>
      <Id>71</Id>
      <BubbleId>1</BubbleId>
      <SubId>1</SubId>
      <Status>To Do</Status>
    </Entry>
    <Entry>
      <PointerOffset>96332</PointerOffset>
      <VoiceId>S201951</VoiceId>
      <JapaneseText>軍の掃討作戦が終わりしだい
病人・子ども・老人・女性を
優先して城内に収容するのです</JapaneseText>
      <EnglishText/>
      <Notes/>
      <SpeakerId>3</SpeakerId>
      <Id>71</Id>
      <BubbleId>2</BubbleId>
      <SubId>1</SubId>
      <Status>To Do</Status>
    </Entry>
    <Entry>
      <PointerOffset>96460</PointerOffset>
      <VoiceId>S201952</VoiceId>
      <JapaneseText>し、しかし、結晶騎士団には
ソーマもなく……ガルデニアも
復活し、もはや世界は…………</JapaneseText>
      <EnglishText/>
      <Notes/>
      <SpeakerId>2</SpeakerId>
      <Id>72</Id>
      <BubbleId>1</BubbleId>
      <SubId>1</SubId>
      <Status>To Do</Status>
    </Entry>
    <Entry>
      <PointerOffset>96588</PointerOffset>
      <VoiceId>S201953</VoiceId>
      <JapaneseText>ソーマがなくとも
傷ついた人に包帯を巻く事も
子どもにパンを配る事もできます</JapaneseText>
      <EnglishText/>
      <Notes/>
      <SpeakerId>3</SpeakerId>
      <Id>73</Id>
      <BubbleId>1</BubbleId>
      <SubId>1</SubId>
      <Status>To Do</Status>
    </Entry>
    <Entry>
      <PointerOffset>96588</PointerOffset>
      <VoiceId>S201954</VoiceId>
      <JapaneseText>……しっかりなさいっ！
あなたはクリードと
戦った勇者なのでしょう？</JapaneseText>
      <EnglishText/>
      <Notes/>
      <SpeakerId>3</SpeakerId>
      <Id>73</Id>
      <BubbleId>2</BubbleId>
      <SubId>1</SubId>
      <Status>To Do</Status>
    </Entry>
    <Entry>
      <PointerOffset>96836</PointerOffset>
      <VoiceId>S201955</VoiceId>
      <JapaneseText>…………見苦しい姿を
お見せしました、陛下。
勅命、謹んで拝します！</JapaneseText>
      <EnglishText/>
      <Notes/>
      <SpeakerId>2</SpeakerId>
      <Id>74</Id>
      <BubbleId>1</BubbleId>
      <SubId>1</SubId>
      <Status>To Do</Status>
    </Entry>
    <Entry>
      <PointerOffset>96964</PointerOffset>
      <VoiceId>S201956</VoiceId>
      <JapaneseText>地方軍と地方教会も連携して
各都市と村落の防備を固め
全力で民衆を守ってください！</JapaneseText>
      <EnglishText/>
      <Notes/>
      <SpeakerId>3</SpeakerId>
      <Id>75</Id>
      <BubbleId>1</BubbleId>
      <SubId>1</SubId>
      <Status>To Do</Status>
    </Entry>
    <Entry>
      <PointerOffset>96964</PointerOffset>
      <VoiceId>S201957</VoiceId>
      <JapaneseText>各大臣は、早急に
全土の被害状況をまとめ
救援物資の手配を！</JapaneseText>
      <EnglishText/>
      <Notes/>
      <SpeakerId>3</SpeakerId>
      <Id>75</Id>
      <BubbleId>2</BubbleId>
      <SubId>1</SubId>
      <Status>To Do</Status>
    </Entry>
    <Entry>
      <PointerOffset>96964</PointerOffset>
      <VoiceId>S201958</VoiceId>
      <JapaneseText>理と和をもって混乱に対処なさい！
私欲を優先させ、無用に争う者は
皇帝の名において厳罰に処します!!</JapaneseText>
      <EnglishText/>
      <Notes/>
      <SpeakerId>3</SpeakerId>
      <Id>75</Id>
      <BubbleId>3</BubbleId>
      <SubId>1</SubId>
      <Status>To Do</Status>
    </Entry>
    <Entry>
      <PointerOffset>97092</PointerOffset>
      <VoiceId>S201959</VoiceId>
      <JapaneseText>……例えそれが
教主と上将であろうとも！</JapaneseText>
      <EnglishText/>
      <Notes/>
      <SpeakerId>3</SpeakerId>
      <Id>76</Id>
      <BubbleId>1</BubbleId>
      <SubId>1</SubId>
      <Status>To Do</Status>
    </Entry>
    <Entry>
      <PointerOffset>97220</PointerOffset>
      <VoiceId>S201960</VoiceId>
      <JapaneseText>ははっ、御意ッ!!</JapaneseText>
      <EnglishText/>
      <Notes/>
      <SpeakerId>1</SpeakerId>
      <Id>77</Id>
      <BubbleId>1</BubbleId>
      <SubId>1</SubId>
      <Status>To Do</Status>
    </Entry>
    <Entry>
      <PointerOffset>98272</PointerOffset>
      <VoiceId>S201962</VoiceId>
      <JapaneseText>お見事です、パライバ様</JapaneseText>
      <EnglishText/>
      <Notes/>
      <SpeakerId>4</SpeakerId>
      <Id>78</Id>
      <BubbleId>1</BubbleId>
      <SubId>1</SubId>
      <Status>To Do</Status>
    </Entry>
    <Entry>
      <PointerOffset>98680</PointerOffset>
      <VoiceId>S201963</VoiceId>
      <JapaneseText>カル……わたくしは、これから
直接民衆に、団結し冷静に行動
するよう訴えます。ですが……</JapaneseText>
      <EnglishText/>
      <Notes/>
      <SpeakerId>3</SpeakerId>
      <Id>79</Id>
      <BubbleId>1</BubbleId>
      <SubId>1</SubId>
      <Status>To Do</Status>
    </Entry>
    <Entry>
      <PointerOffset>98808</PointerOffset>
      <VoiceId>S201964</VoiceId>
      <JapaneseText>この足では立っているだけで
精一杯なのです</JapaneseText>
      <EnglishText/>
      <Notes/>
      <SpeakerId>3</SpeakerId>
      <Id>80</Id>
      <BubbleId>1</BubbleId>
      <SubId>1</SubId>
      <Status>To Do</Status>
    </Entry>
    <Entry>
      <PointerOffset>98808</PointerOffset>
      <VoiceId>S201965</VoiceId>
      <JapaneseText>今、皇帝が弱い姿を見せる訳には
いきません。どうか倒れないよう
側で支えていただけませんか？</JapaneseText>
      <EnglishText/>
      <Notes/>
      <SpeakerId>3</SpeakerId>
      <Id>80</Id>
      <BubbleId>2</BubbleId>
      <SubId>1</SubId>
      <Status>To Do</Status>
    </Entry>
    <Entry>
      <PointerOffset>98936</PointerOffset>
      <VoiceId>S201966</VoiceId>
      <JapaneseText>パライバ様、お手を——
あなたが世界を背負うなら
僕は世界ごとあなたを支えます</JapaneseText>
      <EnglishText/>
      <Notes/>
      <SpeakerId>4</SpeakerId>
      <Id>81</Id>
      <BubbleId>1</BubbleId>
      <SubId>1</SubId>
      <Status>To Do</Status>
    </Entry>
    <Entry>
      <PointerOffset>99064</PointerOffset>
      <VoiceId>S201967</VoiceId>
      <JapaneseText>ありがとう
カルセドニー＝アーカム。
わたくしの騎士——</JapaneseText>
      <EnglishText/>
      <Notes/>
      <SpeakerId>3</SpeakerId>
      <Id>82</Id>
      <BubbleId>1</BubbleId>
      <SubId>1</SubId>
      <Status>To Do</Status>
    </Entry>
    <Entry>
      <PointerOffset>99228</PointerOffset>
      <VoiceId>S201968</VoiceId>
      <JapaneseText>カル様……</JapaneseText>
      <EnglishText/>
      <Notes/>
      <SpeakerId>11</SpeakerId>
      <Id>83</Id>
      <BubbleId>1</BubbleId>
      <SubId>1</SubId>
      <Status>To Do</Status>
    </Entry>
    <Entry>
      <PointerOffset>99356</PointerOffset>
      <VoiceId>S201969</VoiceId>
      <JapaneseText>うう、よかったねぇ……</JapaneseText>
      <EnglishText/>
      <Notes/>
      <SpeakerId>8</SpeakerId>
      <Id>84</Id>
      <BubbleId>1</BubbleId>
      <SubId>1</SubId>
      <Status>To Do</Status>
    </Entry>
    <Entry>
      <PointerOffset>99484</PointerOffset>
      <VoiceId>S201970</VoiceId>
      <JapaneseText>隊長も、やればできるじゃん！</JapaneseText>
      <EnglishText/>
      <Notes/>
      <SpeakerId>5</SpeakerId>
      <Id>85</Id>
      <BubbleId>1</BubbleId>
      <SubId>1</SubId>
      <Status>To Do</Status>
    </Entry>
    <Entry>
      <PointerOffset>99612</PointerOffset>
      <VoiceId>S201971</VoiceId>
      <JapaneseText>よ〜し！　オレたちも
一緒にマリンさんを支えようぜ!!</JapaneseText>
      <EnglishText/>
      <Notes/>
      <SpeakerId>9</SpeakerId>
      <Id>86</Id>
      <BubbleId>1</BubbleId>
      <SubId>1</SubId>
      <Status>To Do</Status>
    </Entry>
    <Entry>
      <PointerOffset>101044</PointerOffset>
      <VoiceId>S201972</VoiceId>
      <JapaneseText>もう〜、&lt;Shing&gt;ってば
ほんとに子どもなんだから！</JapaneseText>
      <EnglishText/>
      <Notes/>
      <SpeakerId>10</SpeakerId>
      <Id>87</Id>
      <BubbleId>1</BubbleId>
      <SubId>1</SubId>
      <Status>To Do</Status>
    </Entry>
    <Entry>
      <PointerOffset>104012</PointerOffset>
      <VoiceId>S201973</VoiceId>
      <JapaneseText>え……だってみんなで
支えてあげた方がいいだろ？
…………あれぇ？？</JapaneseText>
      <EnglishText/>
      <Notes/>
      <SpeakerId>9</SpeakerId>
      <Id>88</Id>
      <BubbleId>1</BubbleId>
      <SubId>1</SubId>
      <Status>To Do</Status>
    </Entry>
    <Entry>
      <PointerOffset>106592</PointerOffset>
      <VoiceId>S202001</VoiceId>
      <JapaneseText>わかりました、リチア様……
ガルデニアによって世界は
『白化』の危機にあるのですね</JapaneseText>
      <EnglishText/>
      <Notes/>
      <SpeakerId>3</SpeakerId>
      <Id>89</Id>
      <BubbleId>1</BubbleId>
      <SubId>1</SubId>
      <Status>To Do</Status>
    </Entry>
    <Entry>
      <PointerOffset>106816</PointerOffset>
      <VoiceId>S202002</VoiceId>
      <JapaneseText>はい。どうか事実を……
そして、あきらめない決意を
人々に伝えてください</JapaneseText>
      <EnglishText/>
      <Notes/>
      <SpeakerId>12</SpeakerId>
      <Id>90</Id>
      <BubbleId>1</BubbleId>
      <SubId>1</SubId>
      <Status>To Do</Status>
    </Entry>
    <Entry>
      <PointerOffset>106944</PointerOffset>
      <VoiceId>S202003</VoiceId>
      <JapaneseText>本物のねむり姫は
とても強い御方だったのですね</JapaneseText>
      <EnglishText/>
      <Notes/>
      <SpeakerId>3</SpeakerId>
      <Id>91</Id>
      <BubbleId>1</BubbleId>
      <SubId>1</SubId>
      <Status>To Do</Status>
    </Entry>
    <Entry>
      <PointerOffset>106944</PointerOffset>
      <VoiceId>S202004</VoiceId>
      <JapaneseText>わたくしも、あなたの勇気を
少しだけ分けていただきますわ</JapaneseText>
      <EnglishText/>
      <Notes/>
      <SpeakerId>3</SpeakerId>
      <Id>91</Id>
      <BubbleId>2</BubbleId>
      <SubId>1</SubId>
      <Status>To Do</Status>
    </Entry>
  </Strings>
  <Strings>
    <Section>NPC</Section>
    <Entry>
      <PointerOffset>42876</PointerOffset>
      <JapaneseText>%s</JapaneseText>
      <EnglishText/>
      <Notes/>
      <SpeakerId>13</SpeakerId>
      <Id>92</Id>
      <BubbleId>1</BubbleId>
      <SubId>1</SubId>
      <Status>To Do</Status>
    </Entry>
    <Entry>
      <PointerOffset>43112</PointerOffset>
      <JapaneseText>−</JapaneseText>
      <EnglishText/>
      <Notes/>
      <SpeakerId>13</SpeakerId>
      <Id>93</Id>
      <BubbleId>1</BubbleId>
      <SubId>1</SubId>
      <Status>To Do</Status>
    </Entry>
    <Entry>
      <PointerOffset>45300</PointerOffset>
      <JapaneseText>para_e022</JapaneseText>
      <EnglishText/>
      <Notes/>
      <SpeakerId>13</SpeakerId>
      <Id>94</Id>
      <BubbleId>1</BubbleId>
      <SubId>1</SubId>
      <Status>To Do</Status>
    </Entry>
    <Entry>
      <PointerOffset>48600</PointerOffset>
      <JapaneseText>para_e023</JapaneseText>
      <EnglishText/>
      <Notes/>
      <SpeakerId>13</SpeakerId>
      <Id>95</Id>
      <BubbleId>1</BubbleId>
      <SubId>1</SubId>
      <Status>To Do</Status>
    </Entry>
    <Entry>
      <PointerOffset>52768</PointerOffset>
      <JapaneseText>para_e022</JapaneseText>
      <EnglishText/>
      <Notes/>
      <SpeakerId>13</SpeakerId>
      <Id>96</Id>
      <BubbleId>1</BubbleId>
      <SubId>1</SubId>
      <Status>To Do</Status>
    </Entry>
    <Entry>
      <PointerOffset>52864</PointerOffset>
      <JapaneseText>para_e024</JapaneseText>
      <EnglishText/>
      <Notes/>
      <SpeakerId>13</SpeakerId>
      <Id>97</Id>
      <BubbleId>1</BubbleId>
      <SubId>1</SubId>
      <Status>To Do</Status>
    </Entry>
    <Entry>
      <PointerOffset>62684</PointerOffset>
      <JapaneseText>shing00_e141</JapaneseText>
      <EnglishText/>
      <Notes/>
      <SpeakerId>13</SpeakerId>
      <Id>98</Id>
      <BubbleId>1</BubbleId>
      <SubId>1</SubId>
      <Status>To Do</Status>
    </Entry>
    <Entry>
      <PointerOffset>62740</PointerOffset>
      <JapaneseText>kohaku00_e141</JapaneseText>
      <EnglishText/>
      <Notes/>
      <SpeakerId>13</SpeakerId>
      <Id>99</Id>
      <BubbleId>1</BubbleId>
      <SubId>1</SubId>
      <Status>To Do</Status>
    </Entry>
    <Entry>
      <PointerOffset>62796</PointerOffset>
      <JapaneseText>hisui00_e141</JapaneseText>
      <EnglishText/>
      <Notes/>
      <SpeakerId>13</SpeakerId>
      <Id>100</Id>
      <BubbleId>1</BubbleId>
      <SubId>1</SubId>
      <Status>To Do</Status>
    </Entry>
    <Entry>
      <PointerOffset>62852</PointerOffset>
      <JapaneseText>innes00_e141</JapaneseText>
      <EnglishText/>
      <Notes/>
      <SpeakerId>13</SpeakerId>
      <Id>101</Id>
      <BubbleId>1</BubbleId>
      <SubId>1</SubId>
      <Status>To Do</Status>
    </Entry>
    <Entry>
      <PointerOffset>62908</PointerOffset>
      <JapaneseText>kunzite00_e141</JapaneseText>
      <EnglishText/>
      <Notes/>
      <SpeakerId>13</SpeakerId>
      <Id>102</Id>
      <BubbleId>1</BubbleId>
      <SubId>1</SubId>
      <Status>To Do</Status>
    </Entry>
    <Entry>
      <PointerOffset>62964</PointerOffset>
      <JapaneseText>beryl00_e013</JapaneseText>
      <EnglishText/>
      <Notes/>
      <SpeakerId>13</SpeakerId>
      <Id>103</Id>
      <BubbleId>1</BubbleId>
      <SubId>1</SubId>
      <Status>To Do</Status>
    </Entry>
    <Entry>
      <PointerOffset>64204</PointerOffset>
      <JapaneseText>beryl00_e141</JapaneseText>
      <EnglishText/>
      <Notes/>
      <SpeakerId>13</SpeakerId>
      <Id>104</Id>
      <BubbleId>1</BubbleId>
      <SubId>1</SubId>
      <Status>To Do</Status>
    </Entry>
    <Entry>
      <PointerOffset>64692</PointerOffset>
      <JapaneseText>innes00_e141</JapaneseText>
      <EnglishText/>
      <Notes/>
      <SpeakerId>13</SpeakerId>
      <Id>105</Id>
      <BubbleId>1</BubbleId>
      <SubId>1</SubId>
      <Status>To Do</Status>
    </Entry>
    <Entry>
      <PointerOffset>64784</PointerOffset>
      <JapaneseText>kohaku00_e141</JapaneseText>
      <EnglishText/>
      <Notes/>
      <SpeakerId>13</SpeakerId>
      <Id>106</Id>
      <BubbleId>1</BubbleId>
      <SubId>1</SubId>
      <Status>To Do</Status>
    </Entry>
    <Entry>
      <PointerOffset>65464</PointerOffset>
      <JapaneseText>chal_e013</JapaneseText>
      <EnglishText/>
      <Notes/>
      <SpeakerId>13</SpeakerId>
      <Id>107</Id>
      <BubbleId>1</BubbleId>
      <SubId>1</SubId>
      <Status>To Do</Status>
    </Entry>
    <Entry>
      <PointerOffset>65756</PointerOffset>
      <JapaneseText>para_ze_e021</JapaneseText>
      <EnglishText/>
      <Notes/>
      <SpeakerId>13</SpeakerId>
      <Id>108</Id>
      <BubbleId>1</BubbleId>
      <SubId>1</SubId>
      <Status>To Do</Status>
    </Entry>
    <Entry>
      <PointerOffset>66628</PointerOffset>
      <JapaneseText>chal_e012</JapaneseText>
      <EnglishText/>
      <Notes/>
      <SpeakerId>13</SpeakerId>
      <Id>109</Id>
      <BubbleId>1</BubbleId>
      <SubId>1</SubId>
      <Status>To Do</Status>
    </Entry>
    <Entry>
      <PointerOffset>67332</PointerOffset>
      <JapaneseText>shing00_e011</JapaneseText>
      <EnglishText/>
      <Notes/>
      <SpeakerId>13</SpeakerId>
      <Id>110</Id>
      <BubbleId>1</BubbleId>
      <SubId>1</SubId>
      <Status>To Do</Status>
    </Entry>
    <Entry>
      <PointerOffset>67556</PointerOffset>
      <JapaneseText>chal_e017</JapaneseText>
      <EnglishText/>
      <Notes/>
      <SpeakerId>13</SpeakerId>
      <Id>111</Id>
      <BubbleId>1</BubbleId>
      <SubId>1</SubId>
      <Status>To Do</Status>
    </Entry>
    <Entry>
      <PointerOffset>67820</PointerOffset>
      <JapaneseText>shing00_e017</JapaneseText>
      <EnglishText/>
      <Notes/>
      <SpeakerId>13</SpeakerId>
      <Id>112</Id>
      <BubbleId>1</BubbleId>
      <SubId>1</SubId>
      <Status>To Do</Status>
    </Entry>
    <Entry>
      <PointerOffset>67916</PointerOffset>
      <JapaneseText>shing00_e016</JapaneseText>
      <EnglishText/>
      <Notes/>
      <SpeakerId>13</SpeakerId>
      <Id>113</Id>
      <BubbleId>1</BubbleId>
      <SubId>1</SubId>
      <Status>To Do</Status>
    </Entry>
    <Entry>
      <PointerOffset>68412</PointerOffset>
      <JapaneseText>shing00_e141</JapaneseText>
      <EnglishText/>
      <Notes/>
      <SpeakerId>13</SpeakerId>
      <Id>114</Id>
      <BubbleId>1</BubbleId>
      <SubId>1</SubId>
      <Status>To Do</Status>
    </Entry>
    <Entry>
      <PointerOffset>71524</PointerOffset>
      <JapaneseText></JapaneseText>
      <EnglishText/>
      <Notes/>
      <SpeakerId>13</SpeakerId>
      <Id>115</Id>
      <BubbleId>1</BubbleId>
      <SubId>1</SubId>
      <Status>To Do</Status>
    </Entry>
    <Entry>
      <PointerOffset>71644</PointerOffset>
      <JapaneseText>para_ze_e021</JapaneseText>
      <EnglishText/>
      <Notes/>
      <SpeakerId>13</SpeakerId>
      <Id>116</Id>
      <BubbleId>1</BubbleId>
      <SubId>1</SubId>
      <Status>To Do</Status>
    </Entry>
    <Entry>
      <PointerOffset>72024</PointerOffset>
      <JapaneseText>kohaku00_e028</JapaneseText>
      <EnglishText/>
      <Notes/>
      <SpeakerId>13</SpeakerId>
      <Id>117</Id>
      <BubbleId>1</BubbleId>
      <SubId>1</SubId>
      <Status>To Do</Status>
    </Entry>
    <Entry>
      <PointerOffset>72256</PointerOffset>
      <JapaneseText>kohaku00_e028</JapaneseText>
      <EnglishText/>
      <Notes/>
      <SpeakerId>13</SpeakerId>
      <Id>118</Id>
      <BubbleId>1</BubbleId>
      <SubId>1</SubId>
      <Status>To Do</Status>
    </Entry>
    <Entry>
      <PointerOffset>72612</PointerOffset>
      <JapaneseText>chal_e016</JapaneseText>
      <EnglishText/>
      <Notes/>
      <SpeakerId>13</SpeakerId>
      <Id>119</Id>
      <BubbleId>1</BubbleId>
      <SubId>1</SubId>
      <Status>To Do</Status>
    </Entry>
    <Entry>
      <PointerOffset>72840</PointerOffset>
      <JapaneseText>shing00_e013</JapaneseText>
      <EnglishText/>
      <Notes/>
      <SpeakerId>13</SpeakerId>
      <Id>120</Id>
      <BubbleId>1</BubbleId>
      <SubId>1</SubId>
      <Status>To Do</Status>
    </Entry>
    <Entry>
      <PointerOffset>73416</PointerOffset>
      <JapaneseText></JapaneseText>
      <EnglishText/>
      <Notes/>
      <SpeakerId>13</SpeakerId>
      <Id>121</Id>
      <BubbleId>1</BubbleId>
      <SubId>1</SubId>
      <Status>To Do</Status>
    </Entry>
    <Entry>
      <PointerOffset>73724</PointerOffset>
      <JapaneseText>kohaku00_e017</JapaneseText>
      <EnglishText/>
      <Notes/>
      <SpeakerId>13</SpeakerId>
      <Id>122</Id>
      <BubbleId>1</BubbleId>
      <SubId>1</SubId>
      <Status>To Do</Status>
    </Entry>
    <Entry>
      <PointerOffset>74500</PointerOffset>
      <JapaneseText>shing00_e016</JapaneseText>
      <EnglishText/>
      <Notes/>
      <SpeakerId>13</SpeakerId>
      <Id>123</Id>
      <BubbleId>1</BubbleId>
      <SubId>1</SubId>
      <Status>To Do</Status>
    </Entry>
    <Entry>
      <PointerOffset>74856</PointerOffset>
      <JapaneseText>chal_e016</JapaneseText>
      <EnglishText/>
      <Notes/>
      <SpeakerId>13</SpeakerId>
      <Id>124</Id>
      <BubbleId>1</BubbleId>
      <SubId>1</SubId>
      <Status>To Do</Status>
    </Entry>
    <Entry>
      <PointerOffset>76956</PointerOffset>
      <JapaneseText>para_ze_e021</JapaneseText>
      <EnglishText/>
      <Notes/>
      <SpeakerId>13</SpeakerId>
      <Id>125</Id>
      <BubbleId>1</BubbleId>
      <SubId>1</SubId>
      <Status>To Do</Status>
    </Entry>
    <Entry>
      <PointerOffset>77712</PointerOffset>
      <JapaneseText>chal_e011</JapaneseText>
      <EnglishText/>
      <Notes/>
      <SpeakerId>13</SpeakerId>
      <Id>126</Id>
      <BubbleId>1</BubbleId>
      <SubId>1</SubId>
      <Status>To Do</Status>
    </Entry>
    <Entry>
      <PointerOffset>77884</PointerOffset>
      <JapaneseText>chal_e017</JapaneseText>
      <EnglishText/>
      <Notes/>
      <SpeakerId>13</SpeakerId>
      <Id>127</Id>
      <BubbleId>1</BubbleId>
      <SubId>1</SubId>
      <Status>To Do</Status>
    </Entry>
    <Entry>
      <PointerOffset>78500</PointerOffset>
      <JapaneseText>para_ze_e021</JapaneseText>
      <EnglishText/>
      <Notes/>
      <SpeakerId>13</SpeakerId>
      <Id>128</Id>
      <BubbleId>1</BubbleId>
      <SubId>1</SubId>
      <Status>To Do</Status>
    </Entry>
    <Entry>
      <PointerOffset>79192</PointerOffset>
      <JapaneseText>chal_e011</JapaneseText>
      <EnglishText/>
      <Notes/>
      <SpeakerId>13</SpeakerId>
      <Id>129</Id>
      <BubbleId>1</BubbleId>
      <SubId>1</SubId>
      <Status>To Do</Status>
    </Entry>
    <Entry>
      <PointerOffset>79324</PointerOffset>
      <JapaneseText>chal_e017</JapaneseText>
      <EnglishText/>
      <Notes/>
      <SpeakerId>13</SpeakerId>
      <Id>130</Id>
      <BubbleId>1</BubbleId>
      <SubId>1</SubId>
      <Status>To Do</Status>
    </Entry>
    <Entry>
      <PointerOffset>79684</PointerOffset>
      <JapaneseText>chal_e011</JapaneseText>
      <EnglishText/>
      <Notes/>
      <SpeakerId>13</SpeakerId>
      <Id>131</Id>
      <BubbleId>1</BubbleId>
      <SubId>1</SubId>
      <Status>To Do</Status>
    </Entry>
    <Entry>
      <PointerOffset>79780</PointerOffset>
      <JapaneseText>chal_e017</JapaneseText>
      <EnglishText/>
      <Notes/>
      <SpeakerId>13</SpeakerId>
      <Id>132</Id>
      <BubbleId>1</BubbleId>
      <SubId>1</SubId>
      <Status>To Do</Status>
    </Entry>
    <Entry>
      <PointerOffset>79872</PointerOffset>
      <JapaneseText>chal_e011</JapaneseText>
      <EnglishText/>
      <Notes/>
      <SpeakerId>13</SpeakerId>
      <Id>133</Id>
      <BubbleId>1</BubbleId>
      <SubId>1</SubId>
      <Status>To Do</Status>
    </Entry>
    <Entry>
      <PointerOffset>80004</PointerOffset>
      <JapaneseText>chal_e017</JapaneseText>
      <EnglishText/>
      <Notes/>
      <SpeakerId>13</SpeakerId>
      <Id>134</Id>
      <BubbleId>1</BubbleId>
      <SubId>1</SubId>
      <Status>To Do</Status>
    </Entry>
    <Entry>
      <PointerOffset>80960</PointerOffset>
      <JapaneseText>para_ze_e021</JapaneseText>
      <EnglishText/>
      <Notes/>
      <SpeakerId>13</SpeakerId>
      <Id>135</Id>
      <BubbleId>1</BubbleId>
      <SubId>1</SubId>
      <Status>To Do</Status>
    </Entry>
    <Entry>
      <PointerOffset>81572</PointerOffset>
      <JapaneseText>chal_e011</JapaneseText>
      <EnglishText/>
      <Notes/>
      <SpeakerId>13</SpeakerId>
      <Id>136</Id>
      <BubbleId>1</BubbleId>
      <SubId>1</SubId>
      <Status>To Do</Status>
    </Entry>
    <Entry>
      <PointerOffset>81952</PointerOffset>
      <JapaneseText>chal_e017</JapaneseText>
      <EnglishText/>
      <Notes/>
      <SpeakerId>13</SpeakerId>
      <Id>137</Id>
      <BubbleId>1</BubbleId>
      <SubId>1</SubId>
      <Status>To Do</Status>
    </Entry>
    <Entry>
      <PointerOffset>85104</PointerOffset>
      <JapaneseText>para_ze_e021</JapaneseText>
      <EnglishText/>
      <Notes/>
      <SpeakerId>13</SpeakerId>
      <Id>138</Id>
      <BubbleId>1</BubbleId>
      <SubId>1</SubId>
      <Status>To Do</Status>
    </Entry>
    <Entry>
      <PointerOffset>85368</PointerOffset>
      <JapaneseText>para_ze_e022</JapaneseText>
      <EnglishText/>
      <Notes/>
      <SpeakerId>13</SpeakerId>
      <Id>139</Id>
      <BubbleId>1</BubbleId>
      <SubId>1</SubId>
      <Status>To Do</Status>
    </Entry>
    <Entry>
      <PointerOffset>87084</PointerOffset>
      <JapaneseText>arcm_e026</JapaneseText>
      <EnglishText/>
      <Notes/>
      <SpeakerId>13</SpeakerId>
      <Id>140</Id>
      <BubbleId>1</BubbleId>
      <SubId>1</SubId>
      <Status>To Do</Status>
    </Entry>
    <Entry>
      <PointerOffset>87140</PointerOffset>
      <JapaneseText>para_e021</JapaneseText>
      <EnglishText/>
      <Notes/>
      <SpeakerId>13</SpeakerId>
      <Id>141</Id>
      <BubbleId>1</BubbleId>
      <SubId>1</SubId>
      <Status>To Do</Status>
    </Entry>
    <Entry>
      <PointerOffset>87196</PointerOffset>
      <JapaneseText>gros_e025</JapaneseText>
      <EnglishText/>
      <Notes/>
      <SpeakerId>13</SpeakerId>
      <Id>142</Id>
      <BubbleId>1</BubbleId>
      <SubId>1</SubId>
      <Status>To Do</Status>
    </Entry>
    <Entry>
      <PointerOffset>88048</PointerOffset>
      <JapaneseText>chal_e011</JapaneseText>
      <EnglishText/>
      <Notes/>
      <SpeakerId>13</SpeakerId>
      <Id>143</Id>
      <BubbleId>1</BubbleId>
      <SubId>1</SubId>
      <Status>To Do</Status>
    </Entry>
    <Entry>
      <PointerOffset>88144</PointerOffset>
      <JapaneseText>para_e025</JapaneseText>
      <EnglishText/>
      <Notes/>
      <SpeakerId>13</SpeakerId>
      <Id>144</Id>
      <BubbleId>1</BubbleId>
      <SubId>1</SubId>
      <Status>To Do</Status>
    </Entry>
    <Entry>
      <PointerOffset>94252</PointerOffset>
      <JapaneseText>para_e026</JapaneseText>
      <EnglishText/>
      <Notes/>
      <SpeakerId>13</SpeakerId>
      <Id>145</Id>
      <BubbleId>1</BubbleId>
      <SubId>1</SubId>
      <Status>To Do</Status>
    </Entry>
    <Entry>
      <PointerOffset>94764</PointerOffset>
      <JapaneseText>para_e027</JapaneseText>
      <EnglishText/>
      <Notes/>
      <SpeakerId>13</SpeakerId>
      <Id>146</Id>
      <BubbleId>1</BubbleId>
      <SubId>1</SubId>
      <Status>To Do</Status>
    </Entry>
    <Entry>
      <PointerOffset>102376</PointerOffset>
      <JapaneseText>kohaku00_e103</JapaneseText>
      <EnglishText/>
      <Notes/>
      <SpeakerId>13</SpeakerId>
      <Id>147</Id>
      <BubbleId>1</BubbleId>
      <SubId>1</SubId>
      <Status>To Do</Status>
    </Entry>
    <Entry>
      <PointerOffset>102432</PointerOffset>
      <JapaneseText>beryl00_e103</JapaneseText>
      <EnglishText/>
      <Notes/>
      <SpeakerId>13</SpeakerId>
      <Id>148</Id>
      <BubbleId>1</BubbleId>
      <SubId>1</SubId>
      <Status>To Do</Status>
    </Entry>
    <Entry>
      <PointerOffset>103256</PointerOffset>
      <JapaneseText>kohaku00_e101</JapaneseText>
      <EnglishText/>
      <Notes/>
      <SpeakerId>13</SpeakerId>
      <Id>149</Id>
      <BubbleId>1</BubbleId>
      <SubId>1</SubId>
      <Status>To Do</Status>
    </Entry>
    <Entry>
      <PointerOffset>103392</PointerOffset>
      <JapaneseText>beryl00_e101</JapaneseText>
      <EnglishText/>
      <Notes/>
      <SpeakerId>13</SpeakerId>
      <Id>150</Id>
      <BubbleId>1</BubbleId>
      <SubId>1</SubId>
      <Status>To Do</Status>
    </Entry>
    <Entry>
      <PointerOffset>106212</PointerOffset>
      <JapaneseText>para_e028</JapaneseText>
      <EnglishText/>
      <Notes/>
      <SpeakerId>13</SpeakerId>
      <Id>151</Id>
      <BubbleId>1</BubbleId>
      <SubId>1</SubId>
      <Status>To Do</Status>
    </Entry>
    <Entry>
      <PointerOffset>106668</PointerOffset>
      <JapaneseText>rich_e016</JapaneseText>
      <EnglishText/>
      <Notes/>
      <SpeakerId>13</SpeakerId>
      <Id>152</Id>
      <BubbleId>1</BubbleId>
      <SubId>1</SubId>
      <Status>To Do</Status>
    </Entry>
    <Entry>
      <PointerOffset>109484</PointerOffset>
      <JapaneseText></JapaneseText>
      <EnglishText/>
      <Notes/>
      <SpeakerId>13</SpeakerId>
      <Id>153</Id>
      <BubbleId>1</BubbleId>
      <SubId>1</SubId>
      <Status>To Do</Status>
    </Entry>
    <Entry>
      <PointerOffset>109540</PointerOffset>
      <JapaneseText>para_ze_e021</JapaneseText>
      <EnglishText/>
      <Notes/>
      <SpeakerId>13</SpeakerId>
      <Id>154</Id>
      <BubbleId>1</BubbleId>
      <SubId>1</SubId>
      <Status>To Do</Status>
    </Entry>
    <Entry>
      <PointerOffset>109792</PointerOffset>
      <JapaneseText>kohaku00_e028</JapaneseText>
      <EnglishText/>
      <Notes/>
      <SpeakerId>13</SpeakerId>
      <Id>155</Id>
      <BubbleId>1</BubbleId>
      <SubId>1</SubId>
      <Status>To Do</Status>
    </Entry>
    <Entry>
      <PointerOffset>109960</PointerOffset>
      <JapaneseText>kohaku00_e028</JapaneseText>
      <EnglishText/>
      <Notes/>
      <SpeakerId>13</SpeakerId>
      <Id>156</Id>
      <BubbleId>1</BubbleId>
      <SubId>1</SubId>
      <Status>To Do</Status>
    </Entry>
    <Entry>
      <PointerOffset>110316</PointerOffset>
      <JapaneseText>chal_e016</JapaneseText>
      <EnglishText/>
      <Notes/>
      <SpeakerId>13</SpeakerId>
      <Id>157</Id>
      <BubbleId>1</BubbleId>
      <SubId>1</SubId>
      <Status>To Do</Status>
    </Entry>
    <Entry>
      <PointerOffset>110544</PointerOffset>
      <JapaneseText>shing00_e013</JapaneseText>
      <EnglishText/>
      <Notes/>
      <SpeakerId>13</SpeakerId>
      <Id>158</Id>
      <BubbleId>1</BubbleId>
      <SubId>1</SubId>
      <Status>To Do</Status>
    </Entry>
    <Entry>
      <PointerOffset>111120</PointerOffset>
      <JapaneseText></JapaneseText>
      <EnglishText/>
      <Notes/>
      <SpeakerId>13</SpeakerId>
      <Id>159</Id>
      <BubbleId>1</BubbleId>
      <SubId>1</SubId>
      <Status>To Do</Status>
    </Entry>
    <Entry>
      <PointerOffset>111428</PointerOffset>
      <JapaneseText>kohaku00_e017</JapaneseText>
      <EnglishText/>
      <Notes/>
      <SpeakerId>13</SpeakerId>
      <Id>160</Id>
      <BubbleId>1</BubbleId>
      <SubId>1</SubId>
      <Status>To Do</Status>
    </Entry>
    <Entry>
      <PointerOffset>111948</PointerOffset>
      <JapaneseText>shing00_e016</JapaneseText>
      <EnglishText/>
      <Notes/>
      <SpeakerId>13</SpeakerId>
      <Id>161</Id>
      <BubbleId>1</BubbleId>
      <SubId>1</SubId>
      <Status>To Do</Status>
    </Entry>
    <Entry>
      <PointerOffset>112176</PointerOffset>
      <JapaneseText>chal_e016</JapaneseText>
      <EnglishText/>
      <Notes/>
      <SpeakerId>13</SpeakerId>
      <Id>162</Id>
      <BubbleId>1</BubbleId>
      <SubId>1</SubId>
      <Status>To Do</Status>
    </Entry>
    <Entry>
      <PointerOffset>113972</PointerOffset>
      <JapaneseText>para_ze_e021</JapaneseText>
      <EnglishText/>
      <Notes/>
      <SpeakerId>13</SpeakerId>
      <Id>163</Id>
      <BubbleId>1</BubbleId>
      <SubId>1</SubId>
      <Status>To Do</Status>
    </Entry>
    <Entry>
      <PointerOffset>114664</PointerOffset>
      <JapaneseText>chal_e011</JapaneseText>
      <EnglishText/>
      <Notes/>
      <SpeakerId>13</SpeakerId>
      <Id>164</Id>
      <BubbleId>1</BubbleId>
      <SubId>1</SubId>
      <Status>To Do</Status>
    </Entry>
    <Entry>
      <PointerOffset>114836</PointerOffset>
      <JapaneseText>chal_e017</JapaneseText>
      <EnglishText/>
      <Notes/>
      <SpeakerId>13</SpeakerId>
      <Id>165</Id>
      <BubbleId>1</BubbleId>
      <SubId>1</SubId>
      <Status>To Do</Status>
    </Entry>
    <Entry>
      <PointerOffset>115196</PointerOffset>
      <JapaneseText>para_ze_e021</JapaneseText>
      <EnglishText/>
      <Notes/>
      <SpeakerId>13</SpeakerId>
      <Id>166</Id>
      <BubbleId>1</BubbleId>
      <SubId>1</SubId>
      <Status>To Do</Status>
    </Entry>
    <Entry>
      <PointerOffset>115824</PointerOffset>
      <JapaneseText>chal_e011</JapaneseText>
      <EnglishText/>
      <Notes/>
      <SpeakerId>13</SpeakerId>
      <Id>167</Id>
      <BubbleId>1</BubbleId>
      <SubId>1</SubId>
      <Status>To Do</Status>
    </Entry>
    <Entry>
      <PointerOffset>115956</PointerOffset>
      <JapaneseText>chal_e017</JapaneseText>
      <EnglishText/>
      <Notes/>
      <SpeakerId>13</SpeakerId>
      <Id>168</Id>
      <BubbleId>1</BubbleId>
      <SubId>1</SubId>
      <Status>To Do</Status>
    </Entry>
    <Entry>
      <PointerOffset>116316</PointerOffset>
      <JapaneseText>chal_e011</JapaneseText>
      <EnglishText/>
      <Notes/>
      <SpeakerId>13</SpeakerId>
      <Id>169</Id>
      <BubbleId>1</BubbleId>
      <SubId>1</SubId>
      <Status>To Do</Status>
    </Entry>
    <Entry>
      <PointerOffset>116412</PointerOffset>
      <JapaneseText>chal_e017</JapaneseText>
      <EnglishText/>
      <Notes/>
      <SpeakerId>13</SpeakerId>
      <Id>170</Id>
      <BubbleId>1</BubbleId>
      <SubId>1</SubId>
      <Status>To Do</Status>
    </Entry>
    <Entry>
      <PointerOffset>116504</PointerOffset>
      <JapaneseText>chal_e011</JapaneseText>
      <EnglishText/>
      <Notes/>
      <SpeakerId>13</SpeakerId>
      <Id>171</Id>
      <BubbleId>1</BubbleId>
      <SubId>1</SubId>
      <Status>To Do</Status>
    </Entry>
    <Entry>
      <PointerOffset>116636</PointerOffset>
      <JapaneseText>chal_e017</JapaneseText>
      <EnglishText/>
      <Notes/>
      <SpeakerId>13</SpeakerId>
      <Id>172</Id>
      <BubbleId>1</BubbleId>
      <SubId>1</SubId>
      <Status>To Do</Status>
    </Entry>
    <Entry>
      <PointerOffset>117464</PointerOffset>
      <JapaneseText>para_ze_e021</JapaneseText>
      <EnglishText/>
      <Notes/>
      <SpeakerId>13</SpeakerId>
      <Id>173</Id>
      <BubbleId>1</BubbleId>
      <SubId>1</SubId>
      <Status>To Do</Status>
    </Entry>
    <Entry>
      <PointerOffset>118012</PointerOffset>
      <JapaneseText>chal_e011</JapaneseText>
      <EnglishText/>
      <Notes/>
      <SpeakerId>13</SpeakerId>
      <Id>174</Id>
      <BubbleId>1</BubbleId>
      <SubId>1</SubId>
      <Status>To Do</Status>
    </Entry>
    <Entry>
      <PointerOffset>118264</PointerOffset>
      <JapaneseText>chal_e017</JapaneseText>
      <EnglishText/>
      <Notes/>
      <SpeakerId>13</SpeakerId>
      <Id>175</Id>
      <BubbleId>1</BubbleId>
      <SubId>1</SubId>
      <Status>To Do</Status>
    </Entry>
    <Entry>
      <PointerOffset>120840</PointerOffset>
      <JapaneseText>para_ze_e021</JapaneseText>
      <EnglishText/>
      <Notes/>
      <SpeakerId>13</SpeakerId>
      <Id>176</Id>
      <BubbleId>1</BubbleId>
      <SubId>1</SubId>
      <Status>To Do</Status>
    </Entry>
    <Entry>
      <PointerOffset>121104</PointerOffset>
      <JapaneseText>para_ze_e022</JapaneseText>
      <EnglishText/>
      <Notes/>
      <SpeakerId>13</SpeakerId>
      <Id>177</Id>
      <BubbleId>1</BubbleId>
      <SubId>1</SubId>
      <Status>To Do</Status>
    </Entry>
    <Entry>
      <PointerOffset>122616</PointerOffset>
      <JapaneseText>arcm_e026</JapaneseText>
      <EnglishText/>
      <Notes/>
      <SpeakerId>13</SpeakerId>
      <Id>178</Id>
      <BubbleId>1</BubbleId>
      <SubId>1</SubId>
      <Status>To Do</Status>
    </Entry>
    <Entry>
      <PointerOffset>122672</PointerOffset>
      <JapaneseText>para_e021</JapaneseText>
      <EnglishText/>
      <Notes/>
      <SpeakerId>13</SpeakerId>
      <Id>179</Id>
      <BubbleId>1</BubbleId>
      <SubId>1</SubId>
      <Status>To Do</Status>
    </Entry>
    <Entry>
      <PointerOffset>122728</PointerOffset>
      <JapaneseText>gros_e025</JapaneseText>
      <EnglishText/>
      <Notes/>
      <SpeakerId>13</SpeakerId>
      <Id>180</Id>
      <BubbleId>1</BubbleId>
      <SubId>1</SubId>
      <Status>To Do</Status>
    </Entry>
    <Entry>
      <PointerOffset>123516</PointerOffset>
      <JapaneseText>chal_e011</JapaneseText>
      <EnglishText/>
      <Notes/>
      <SpeakerId>13</SpeakerId>
      <Id>181</Id>
      <BubbleId>1</BubbleId>
      <SubId>1</SubId>
      <Status>To Do</Status>
    </Entry>
    <Entry>
      <PointerOffset>123612</PointerOffset>
      <JapaneseText>para_e025</JapaneseText>
      <EnglishText/>
      <Notes/>
      <SpeakerId>13</SpeakerId>
      <Id>182</Id>
      <BubbleId>1</BubbleId>
      <SubId>1</SubId>
      <Status>To Do</Status>
    </Entry>
    <Entry>
      <PointerOffset>128184</PointerOffset>
      <JapaneseText>para_e026</JapaneseText>
      <EnglishText/>
      <Notes/>
      <SpeakerId>13</SpeakerId>
      <Id>183</Id>
      <BubbleId>1</BubbleId>
      <SubId>1</SubId>
      <Status>To Do</Status>
    </Entry>
    <Entry>
      <PointerOffset>128568</PointerOffset>
      <JapaneseText>para_e027</JapaneseText>
      <EnglishText/>
      <Notes/>
      <SpeakerId>13</SpeakerId>
      <Id>184</Id>
      <BubbleId>1</BubbleId>
      <SubId>1</SubId>
      <Status>To Do</Status>
    </Entry>
  </Strings>
</SceneText>
