<SceneText>
  <Speakers>
    <Section>Speaker</Section>
    <Entry>
      <PointerOffset/>
      <JapaneseText>Variable</JapaneseText>
      <EnglishText/>
      <Notes/>
      <Id>1</Id>
      <Status>To Do</Status>
    </Entry>
  </Speakers>
  <Strings>
    <Section>NPC</Section>
    <Entry>
      <PointerOffset>36516</PointerOffset>
      <JapaneseText>%s</JapaneseText>
      <EnglishText/>
      <Notes/>
      <SpeakerId>1</SpeakerId>
      <Id>1</Id>
      <BubbleId>1</BubbleId>
      <SubId>1</SubId>
      <Status>To Do</Status>
    </Entry>
    <Entry>
      <PointerOffset>36752</PointerOffset>
      <JapaneseText>−</JapaneseText>
      <EnglishText/>
      <Notes/>
      <SpeakerId>1</SpeakerId>
      <Id>2</Id>
      <BubbleId>1</BubbleId>
      <SubId>1</SubId>
      <Status>To Do</Status>
    </Entry>
    <Entry>
      <PointerOffset>50988</PointerOffset>
      <JapaneseText>shing00_e013</JapaneseText>
      <EnglishText/>
      <Notes/>
      <SpeakerId>1</SpeakerId>
      <Id>3</Id>
      <BubbleId>1</BubbleId>
      <SubId>1</SubId>
      <Status>To Do</Status>
    </Entry>
    <Entry>
      <PointerOffset>51124</PointerOffset>
      <JapaneseText>hisui00_e013</JapaneseText>
      <EnglishText/>
      <Notes/>
      <SpeakerId>1</SpeakerId>
      <Id>4</Id>
      <BubbleId>1</BubbleId>
      <SubId>1</SubId>
      <Status>To Do</Status>
    </Entry>
    <Entry>
      <PointerOffset>51260</PointerOffset>
      <JapaneseText>kohaku00_e013</JapaneseText>
      <EnglishText/>
      <Notes/>
      <SpeakerId>1</SpeakerId>
      <Id>5</Id>
      <BubbleId>1</BubbleId>
      <SubId>1</SubId>
      <Status>To Do</Status>
    </Entry>
    <Entry>
      <PointerOffset>51396</PointerOffset>
      <JapaneseText>innes00_e013</JapaneseText>
      <EnglishText/>
      <Notes/>
      <SpeakerId>1</SpeakerId>
      <Id>6</Id>
      <BubbleId>1</BubbleId>
      <SubId>1</SubId>
      <Status>To Do</Status>
    </Entry>
    <Entry>
      <PointerOffset>51532</PointerOffset>
      <JapaneseText>beryl00_e013</JapaneseText>
      <EnglishText/>
      <Notes/>
      <SpeakerId>1</SpeakerId>
      <Id>7</Id>
      <BubbleId>1</BubbleId>
      <SubId>1</SubId>
      <Status>To Do</Status>
    </Entry>
    <Entry>
      <PointerOffset>51668</PointerOffset>
      <JapaneseText>kunzite00_e013</JapaneseText>
      <EnglishText/>
      <Notes/>
      <SpeakerId>1</SpeakerId>
      <Id>8</Id>
      <BubbleId>1</BubbleId>
      <SubId>1</SubId>
      <Status>To Do</Status>
    </Entry>
    <Entry>
      <PointerOffset>52564</PointerOffset>
      <JapaneseText>shing00_e012</JapaneseText>
      <EnglishText/>
      <Notes/>
      <SpeakerId>1</SpeakerId>
      <Id>9</Id>
      <BubbleId>1</BubbleId>
      <SubId>1</SubId>
      <Status>To Do</Status>
    </Entry>
    <Entry>
      <PointerOffset>52700</PointerOffset>
      <JapaneseText>hisui00_e012</JapaneseText>
      <EnglishText/>
      <Notes/>
      <SpeakerId>1</SpeakerId>
      <Id>10</Id>
      <BubbleId>1</BubbleId>
      <SubId>1</SubId>
      <Status>To Do</Status>
    </Entry>
    <Entry>
      <PointerOffset>52836</PointerOffset>
      <JapaneseText>kohaku00_e012</JapaneseText>
      <EnglishText/>
      <Notes/>
      <SpeakerId>1</SpeakerId>
      <Id>11</Id>
      <BubbleId>1</BubbleId>
      <SubId>1</SubId>
      <Status>To Do</Status>
    </Entry>
    <Entry>
      <PointerOffset>52972</PointerOffset>
      <JapaneseText>innes00_e012</JapaneseText>
      <EnglishText/>
      <Notes/>
      <SpeakerId>1</SpeakerId>
      <Id>12</Id>
      <BubbleId>1</BubbleId>
      <SubId>1</SubId>
      <Status>To Do</Status>
    </Entry>
    <Entry>
      <PointerOffset>53108</PointerOffset>
      <JapaneseText>beryl00_e012</JapaneseText>
      <EnglishText/>
      <Notes/>
      <SpeakerId>1</SpeakerId>
      <Id>13</Id>
      <BubbleId>1</BubbleId>
      <SubId>1</SubId>
      <Status>To Do</Status>
    </Entry>
    <Entry>
      <PointerOffset>53244</PointerOffset>
      <JapaneseText>kunzite00_e012</JapaneseText>
      <EnglishText/>
      <Notes/>
      <SpeakerId>1</SpeakerId>
      <Id>14</Id>
      <BubbleId>1</BubbleId>
      <SubId>1</SubId>
      <Status>To Do</Status>
    </Entry>
    <Entry>
      <PointerOffset>54140</PointerOffset>
      <JapaneseText>shing00_e018</JapaneseText>
      <EnglishText/>
      <Notes/>
      <SpeakerId>1</SpeakerId>
      <Id>15</Id>
      <BubbleId>1</BubbleId>
      <SubId>1</SubId>
      <Status>To Do</Status>
    </Entry>
    <Entry>
      <PointerOffset>54264</PointerOffset>
      <JapaneseText>shing00_e017</JapaneseText>
      <EnglishText/>
      <Notes/>
      <SpeakerId>1</SpeakerId>
      <Id>16</Id>
      <BubbleId>1</BubbleId>
      <SubId>1</SubId>
      <Status>To Do</Status>
    </Entry>
    <Entry>
      <PointerOffset>54400</PointerOffset>
      <JapaneseText>hisui00_e018</JapaneseText>
      <EnglishText/>
      <Notes/>
      <SpeakerId>1</SpeakerId>
      <Id>17</Id>
      <BubbleId>1</BubbleId>
      <SubId>1</SubId>
      <Status>To Do</Status>
    </Entry>
    <Entry>
      <PointerOffset>54524</PointerOffset>
      <JapaneseText>hisui00_e017</JapaneseText>
      <EnglishText/>
      <Notes/>
      <SpeakerId>1</SpeakerId>
      <Id>18</Id>
      <BubbleId>1</BubbleId>
      <SubId>1</SubId>
      <Status>To Do</Status>
    </Entry>
    <Entry>
      <PointerOffset>54660</PointerOffset>
      <JapaneseText>kohaku00_e018</JapaneseText>
      <EnglishText/>
      <Notes/>
      <SpeakerId>1</SpeakerId>
      <Id>19</Id>
      <BubbleId>1</BubbleId>
      <SubId>1</SubId>
      <Status>To Do</Status>
    </Entry>
    <Entry>
      <PointerOffset>54784</PointerOffset>
      <JapaneseText>kohaku00_e017</JapaneseText>
      <EnglishText/>
      <Notes/>
      <SpeakerId>1</SpeakerId>
      <Id>20</Id>
      <BubbleId>1</BubbleId>
      <SubId>1</SubId>
      <Status>To Do</Status>
    </Entry>
    <Entry>
      <PointerOffset>54920</PointerOffset>
      <JapaneseText>innes00_e018</JapaneseText>
      <EnglishText/>
      <Notes/>
      <SpeakerId>1</SpeakerId>
      <Id>21</Id>
      <BubbleId>1</BubbleId>
      <SubId>1</SubId>
      <Status>To Do</Status>
    </Entry>
    <Entry>
      <PointerOffset>55044</PointerOffset>
      <JapaneseText>innes00_e017</JapaneseText>
      <EnglishText/>
      <Notes/>
      <SpeakerId>1</SpeakerId>
      <Id>22</Id>
      <BubbleId>1</BubbleId>
      <SubId>1</SubId>
      <Status>To Do</Status>
    </Entry>
    <Entry>
      <PointerOffset>55180</PointerOffset>
      <JapaneseText>beryl00_e018</JapaneseText>
      <EnglishText/>
      <Notes/>
      <SpeakerId>1</SpeakerId>
      <Id>23</Id>
      <BubbleId>1</BubbleId>
      <SubId>1</SubId>
      <Status>To Do</Status>
    </Entry>
    <Entry>
      <PointerOffset>55304</PointerOffset>
      <JapaneseText>beryl00_e017</JapaneseText>
      <EnglishText/>
      <Notes/>
      <SpeakerId>1</SpeakerId>
      <Id>24</Id>
      <BubbleId>1</BubbleId>
      <SubId>1</SubId>
      <Status>To Do</Status>
    </Entry>
    <Entry>
      <PointerOffset>55440</PointerOffset>
      <JapaneseText>kunzite00_e018</JapaneseText>
      <EnglishText/>
      <Notes/>
      <SpeakerId>1</SpeakerId>
      <Id>25</Id>
      <BubbleId>1</BubbleId>
      <SubId>1</SubId>
      <Status>To Do</Status>
    </Entry>
    <Entry>
      <PointerOffset>55564</PointerOffset>
      <JapaneseText>kunzite00_e017</JapaneseText>
      <EnglishText/>
      <Notes/>
      <SpeakerId>1</SpeakerId>
      <Id>26</Id>
      <BubbleId>1</BubbleId>
      <SubId>1</SubId>
      <Status>To Do</Status>
    </Entry>
    <Entry>
      <PointerOffset>55788</PointerOffset>
      <JapaneseText>shing00_e011</JapaneseText>
      <EnglishText/>
      <Notes/>
      <SpeakerId>1</SpeakerId>
      <Id>27</Id>
      <BubbleId>1</BubbleId>
      <SubId>1</SubId>
      <Status>To Do</Status>
    </Entry>
    <Entry>
      <PointerOffset>55924</PointerOffset>
      <JapaneseText>hisui00_e011</JapaneseText>
      <EnglishText/>
      <Notes/>
      <SpeakerId>1</SpeakerId>
      <Id>28</Id>
      <BubbleId>1</BubbleId>
      <SubId>1</SubId>
      <Status>To Do</Status>
    </Entry>
    <Entry>
      <PointerOffset>56060</PointerOffset>
      <JapaneseText>kohaku00_e011</JapaneseText>
      <EnglishText/>
      <Notes/>
      <SpeakerId>1</SpeakerId>
      <Id>29</Id>
      <BubbleId>1</BubbleId>
      <SubId>1</SubId>
      <Status>To Do</Status>
    </Entry>
    <Entry>
      <PointerOffset>56196</PointerOffset>
      <JapaneseText>innes00_e011</JapaneseText>
      <EnglishText/>
      <Notes/>
      <SpeakerId>1</SpeakerId>
      <Id>30</Id>
      <BubbleId>1</BubbleId>
      <SubId>1</SubId>
      <Status>To Do</Status>
    </Entry>
    <Entry>
      <PointerOffset>56332</PointerOffset>
      <JapaneseText>beryl00_e011</JapaneseText>
      <EnglishText/>
      <Notes/>
      <SpeakerId>1</SpeakerId>
      <Id>31</Id>
      <BubbleId>1</BubbleId>
      <SubId>1</SubId>
      <Status>To Do</Status>
    </Entry>
    <Entry>
      <PointerOffset>56468</PointerOffset>
      <JapaneseText>kunzite00_e011</JapaneseText>
      <EnglishText/>
      <Notes/>
      <SpeakerId>1</SpeakerId>
      <Id>32</Id>
      <BubbleId>1</BubbleId>
      <SubId>1</SubId>
      <Status>To Do</Status>
    </Entry>
    <Entry>
      <PointerOffset>60196</PointerOffset>
      <JapaneseText>水の供給量が変化しました</JapaneseText>
      <EnglishText/>
      <Notes/>
      <SpeakerId>1</SpeakerId>
      <Id>33</Id>
      <BubbleId>1</BubbleId>
      <SubId>1</SubId>
      <Status>To Do</Status>
    </Entry>
    <Entry>
      <PointerOffset>60924</PointerOffset>
      <JapaneseText>drad05</JapaneseText>
      <EnglishText/>
      <Notes/>
      <SpeakerId>1</SpeakerId>
      <Id>34</Id>
      <BubbleId>1</BubbleId>
      <SubId>1</SubId>
      <Status>To Do</Status>
    </Entry>
  </Strings>
</SceneText>
